Workbook

Sheet FRONT PAGE
A14: India’s largest producer of zinc, lead, and silver
A15: Subsidiary of Vedanta Limited
A16: Operates integrated mining and smelting units mainly in Rajasthan
A17: Supplies metals to construction, automobile, infrastructure, and electronics industries
A18: Known for low production cost, strong profits, and high dividend payouts
A19: Major player in India’s non-ferrous metals sector
A22: Company Name: Hindustan Zinc Limited
A23: Company Symbol (Ticker): HINDZINC
A24: ISIN: INE267A01025
A25: Industry: Metals & Mining
A26: Sector: Non-Ferrous Metals
A27: Stock Exchange (Shares Listed): NSE, BSE
... A41: Primary Shares Outstanding (cr): 422

Sheet SUMMARY TABLES
A2: P&L SMMARY
A3: Year | B3: Revenue | C3: EBITDA | D3: EBIT | E3: PAT
A4: 2021 | B4: 22071 | C4: 15844 | D4: 15132 | E4: 12152
A5: 2022 | B5: 28790 | C5: 15575 | D5: 13877 | E5: 9116
A6: 2023 | B6: 33272 | C6: 16680 | D6: 14795 | E6: 9685
A7: 2024 | B7: 28082 | C7: 12806 | D7: 10412 | E7: 6909
A8: 2025 | B8: 33041 | C8: 16346 | D8: 13689 | E8: 9394
A9: 2026E | B9: 39019 | C9: 19483 | D9: -1041 | E9: -1507
A10: 2027E | B10: 62511 | C10: 31160 | D10: 27705 | E10: 20591
A12: PROFITABLITY SUMMARY
A13: Year | B13: EBITDA % | C13: EBIT % | D13: Net Margin %
A14: 2021 | B14: 0.718 | C14: 0.686 | D14: 0.551
A15: 2022 | B15: 0.541 | C15: 0.482 | D15: 0.317
A16: 2023 | B16: 0.501 | C16: 0.445 | D16: 0.291
A17: 2024 | B17: 0.456 | C17: 0.371 | D17: 0.246
A18: 2025 | B18: 0.495 | C18: 0.414 | D18: 0.284
A19: 2026E | B19: 0.499
A20: 2027E | B20: 0.498 | C20: 0.443 | D20: 0.329
A22: BALANCE SHEET SUMMARY (IN Cr)
A23: Year | B23: Total Assets | C23: Equity | D23: Liabilities
A24: 2021 | B24: 36126 | C24: 25361 | D24: 36126
A25: 2022 | B25: 41824 | C25: 28269 | D25: 41824
A26: 2023 | B26: 47512 | C26: 31874 | D26: 47512
A27: 2024 | B27: 51364 | C27: 34217 | D27: 51364
A28: 2025 | B28: 56772 | C28: 37985 | D28: 56772
A29: 2026E | B29: 63984 | C29: 41765 | D29: 63984
A30: 2027E | B30: 71908 | C30: 46153 | D30: 71908
A32: CASH FLOW SUMMARY (IN Cr)
A33: Year | B33: Operating CF | C33: Investing CF | D33: Financing CF | E33: Net Change
A34: 2021 | B34: Strong positive | C34: Negative (capex) | D34: Negative (dividends) | E34: Stable
A35: 2022 | B35: Strong positive | C35: Negative | D35: Negative | E35: Stable
A36: 2023 | B36: Strong positive | C36: Negative | D36: Negative | E36: Slight drop
A37: 2024 | B37: Moderate | C37: Capex heavy | D37: Dividend heavy | E37: Lower cash
A38: 2025 | B38: Recovery | C38: Capex continues | D38: Dividend payout | E38: Stable
A39: 2026E | B39: Improving | C39: Expansion capex | D39: Financing support | E39: Growth
A40: 2027E | B40: Very strong | C40: Expansion investment | D40: Stable | E40: Strong rise
A42: GROWTH SUMMARY
A43: Year | B43: Revenue Growth | C43: PAT Growth
A44: 2022 | B44: 0.304 | C44: -0.25
A45: 2023 | B45: 0.156 | C45: 0.062
A46: 2024 | B46: -0.156 | C46: -0.287
A47: 2025 | B47: 0.177 | C47: 0.36
A48: 2026E | B48: 0.181 | C48: Negative
A49: 2027E | B49: 0.602 | C49: Strong rebound
A51: PERFORMANCE SUMMARY
A52: Area | B52: Observation
A53: Revenue | B53: Cyclical but long-term upward trend
A54: Margins | B54: Extremely high due to mining economics
A55: Costs | B55: Power & royalty dominate cost structure
A56: Debt risk | B56: Low leverage, strong cash generation
A57: Profit volatility | B57: Commodity price driven
A58: Outlook | B58: Strong long-term but cyclical earnings

Sheet CHARTS
A2: FINANCIAL DATA CHARTS
A3: Particular | B3: 2021 | C3: 2022 | D3: 2023 | E3: 2024 | F3: 2025 | G3: 2026E | H3: 2027E
A4: Revenue | B4: 22071 | C4: 28790 | D4: 33272 | E4: 28082 | F4: 33041 | G4: 39019 | H4: 62511
A5: Revenue Growth % | B5: — | C5: 0.304 | D5: 0.156 | E5: -0.156 | F5: 0.177 | G5: 0.181 | H5: 0.602
A6: EBITDA | B6: 15844 | C6: 15575 | D6: 16680 | E6: 12806 | F6: 16346 | G6: 19483 | H6: 31160
A7: EBITDA Margin % | B7: 0.718 | C7: 0.541 | D7: 0.501 | E7: 0.456 | F7: 0.495 | G7: 0.499 | H7: 0.498
A8: EBIT | B8: 15132 | C8: 13877 | D8: 14795 | E8: 10412 | F8: 13689 | G8: -1041 | H8: 27705
A9: EBIT Margin % | B9: 0.686 | C9: 0.482 | D9: 0.445 | E9: 0.371 | F9: 0.414 | G9: __ | H9: 0.443
A10: Net Profit | B10: 12152 | C10: 9116 | D10: 9685 | E10: 6909 | F10: 9394 | G10: -1507 | H10: 20591
A11: Net Margin % | B11: 0.551 | C11: 0.317 | D11: 0.291 | E11: 0.246 | F11: 0.284 | G11: NEG | H11: 0.329

Sheet P&L 
A2: Hindustan Zinc | B2: 44286 | C2: 44651 | D2: 45016 | E2: 45382 | F2: 45747 | G2: 46112 | H2: 46477
A3: Profit & Loss Account | B3: Y | C3: Y | D3: Y | E3: Y | F3: Y | G3: Y | H3: Y
A4: (in INR Crores) | B4: Act | C4: Act | D4: Act | E4: Act | F4: Act | G4: Est | H4: Est
A6: Revenue from operations | B6: 22071 | C6: 28790 | D6: 33272 | E6: 28082 | F6: 33041 | G6: ='Revenue model'!G15 -> 3901.9 | H6: ='Revenue model'!H15 -> 62510.717
A7: Excise duty | B7: 0 | C7: 0 | D7: 0 | E7: 0 | F7: 0 | G7: 0 | H7: 0 | K7: Revenue trend shows long-term growth with temporary dips → business demand is stable but cyclical.
A8: Net Revenue | B8: =B6-B7 -> 22071 | C8: =C6-C7 -> 28790 | D8: =D6-D7 -> 33272 | E8: =E6-E7 -> 28082 | F8: =F6-F7 -> 33041 | G8: =G6-G7 -> 3901.9 | H8: =H6-H7 -> 62510.717 | K8: Costs (power, royalty, fuel) are rising → margins depend on commodity prices and efficiency
K9: Strong EBITDA history → high operating leverage.
A10: Cost of Goods Sold | B10: =B11+B12+B13 -> 4730 | C10: =C11+C12+C13 -> 5841 | D10: =D11+D12+D13 -> 7636 | E10: =E11+E12+E13 -> 6203 | F10: =F11+F12+F13 -> 6741 | G10: =G11+G12+G13 -> 836.25651 | H10: =H11+H12+H13 -> 13397.467 | K10: Increasing depreciation → ongoing expansion/capex.
A11: Power and fuel | B11: 1732 | C11: 2452 | D11: 3711 | E11: 2843 | F11: 2702 | G11: =G38 -> 357.56552 | H11: =H38 -> 5892.9968 | K11: Debt costs stable → financial risk controlled
A12: Mining Royalty | B12: 2759 | C12: 3667 | D12: 4068 | E12: 3517 | F12: 4103 | G12: =G41 -> 487.00446 | H12: =H41 -> 7799.6763 | K12: Overall: Strong fundamentals, cyclical earnings, positive long-term outlook with short-term volatility.
A13: Changes in inventories of finished goods | B13: 239 | C13: -278 | D13: -143 | E13: -157 | F13: -64 | G13: =G44 -> -8.3134715 | H13: =H44 -> -295.20583
A14: Gross Profit | B14: =B8-B1 -> 22071 | C14: =C8-C10 -> 22949 | D14: =D8-D10 -> 25636 | E14: =E8-E10 -> 21879 | F14: =F8-F10 -> 26300 | G14: =G8-G10 -> 3065.6435 | H14: =H8-H10 -> 49113.249
A16: Selling & General Adm Expenses
A17: Employee benefits expense | B17: 760 | C17: 718 | D17: 845 | E17: 828 | F17: 886 | G17: =G47 -> 110.08861 | H17: =H47 -> 1685.9177
A18: Other expenses | B18: 5467 | C18: 6656 | D18: 8111 | E18: 8245 | F18: 9068 | G18: =G50 -> 1007.2535 | H18: =H50 -> 16267.36
A19: EBITDA | B19: =B14-B17-B18 -> 15844 | C19: =C14-C17-C18 -> 15575 | D19: =D14-D17-D18 -> 16680 | E19: =E14-E17-E18 -> 12806 | F19: =F14-F17-F18 -> 16346 | G19: =G14-G17-G18 -> 1948.3013 | H19: =H14-H17-H18 -> 31159.972
A21: Other income | B21: 1819 | C21: 1216 | D21: 1379 | E21: 1074 | F21: 983 | G21: =G22*('Balance sheet'!G12+'Balance sheet'!G24) -> 1114.7611 | H21: =H22*('Balance sheet'!H12+'Balance sheet'!H24) -> 1057.7246 | I21: based on investment
A22: % of investment | B22: =B21/('Balance sheet'!B12+'Balance sheet'!B24) -> 0.14038744 | C22: =C21/('Balance sheet'!C12+'Balance sheet'!C24) -> 0.080786606 | D22: =D21/('Balance sheet'!D12+'Balance sheet'!D24) -> 0.13644009 | E22: =E21/('Balance sheet'!E12+'Balance sheet'!E24) -> 0.10275545 | F22: =F21/('Balance sheet'!F12+'Balance sheet'!F24) -> 0.098576013 | G22: =AVERAGE(B22:F22) -> 0.11178912 | H22: =AVERAGE(C22:G22) -> 0.10606946
A23: Depreciation and amortization expense | B23: 2531 | C23: 2914 | D23: 3264 | E23: 3468 | F23: 3640 | G23: =G24*'Capex model'!G6 -> 4103.6177 | H23: =H24*'Capex model'!H6 -> 4512.8743 | I23: based on FA
A24: % of Gross Block | B24: =B23/'Capex model'!B6 -> 0.079473734 | C24: =C23/'Capex model'!C6 -> 0.083169221 | D24: =D23/'Capex model'!D6 -> 0.085865362 | E24: =E23/'Capex model'!E6 -> 0.083141542 | F24: =F23/'Capex model'!F6 -> 0.079850828 | G24: =AVERAGE(B24:F24) -> 0.082300137 | H24: =AVERAGE(C24:G24) -> 0.082865418
A25: EBIT | B25: =B19+B21-B23 -> 15132 | C25: =C19+C21-C23 -> 13877 | D25: =D19+D21-D23 -> 14795 | E25: =E19+E21-E23 -> 10412 | F25: =F19+F21-F23 -> 13689 | G25: =G19+G21-G23 -> -1040.5552 | H25: =H19+H21-H23 -> 27704.822
A27: Finance costs | B27: 386 | C27: 290 | D27: 333 | E27: 955 | F27: 1095 | G27: =G28*('Balance sheet'!G45+'Balance sheet'!G46+'Balance sheet'!G55+'Balance sheet'!G56) -> 875.09541 | H27: =H28*('Balance sheet'!H45+'Balance sheet'!H46+'Balance sheet'!H55+'Balance sheet'!H56) -> 919.31697 | I27: Based on browwoings & lease
A28: % of borowwings & lease | B28: =B27/('Balance sheet'!B45+'Balance sheet'!B46+'Balance sheet'!B55+'Balance sheet'!B56) -> 0.059632319 | C28: =C27/('Balance sheet'!C45+'Balance sheet'!C46+'Balance sheet'!C55+'Balance sheet'!C56) -> 0.10196906 | D28: =D27/('Balance sheet'!D45+'Balance sheet'!D46+'Balance sheet'!D55+'Balance sheet'!D56) -> 0.028027944 | E28: =E27/('Balance sheet'!E45+'Balance sheet'!E46+'Balance sheet'!E55+'Balance sheet'!E56) -> 0.10949324 | F28: =F27/('Balance sheet'!F45+'Balance sheet'!F46+'Balance sheet'!F55+'Balance sheet'!F56) -> 0.09984499 | G28: =AVERAGE(B28:F28) -> 0.079793509 | H28: =AVERAGE(C28:G28) -> 0.083825747
A29: PBT | B29: =B25-B27 -> 14746 | C29: =C25-C27 -> 13587 | D29: =D25-D27 -> 14462 | E29: =E25-E27 -> 9457 | F29: =F25-F27 -> 12594 | G29: =G25-G27 -> -1915.6506 | H29: =H25-H27 -> 26785.505
A31: Current tax | B31: 1827 | C31: 2445 | D31: 3431 | E31: 2549 | F31: 3226 | G31: =G32*G29 -> -408.71608 | H31: =H32*H29 -> 6194.0926
A32: % of PBT | B32: =B31/B29 -> 0.12389801 | C32: =C31/C29 -> 0.17995142 | D32: =D31/D29 -> 0.23724243 | E32: =E31/E29 -> 0.26953579 | F32: =F31/F29 -> 0.25615372 | G32: =AVERAGE(B32:F32) -> 0.21335628 | H32: =AVERAGE(C32:G32) -> 0.23124793
A33: Deferred tax | B33: 767 | C33: 2026 | D33: 1346 | E33: -1 | F33: -26 | G33: 0 | H33: 0 | I33: Uncertain
A34: PAT | B34: =B29-B31-B33 -> 12152 | C34: =C29-C31-C33 -> 9116 | D34: =D29-D31-D33 -> 9685 | E34: =E29-E31-E33 -> 6909 | F34: =F29-F31-F33 -> 9394 | G34: =G29-G31-G33 -> -1506.9346 | H34: =H29-H31-H33 -> 20591.413
A36: ASSUMTIONS
A38: =A11 -> Power and fuel | B38: =B11 -> 1732 | C38: =C11 -> 2452 | D38: =D11 -> 3711 | E38: =E11 -> 2843 | F38: =F11 -> 2702 | G38: =G39*G8 -> 357.56552 | H38: =H39*H8 -> 5892.9968
A39: % of Net Revenue | B39: =B38/B8 -> 0.078474016 | C39: =C38/C8 -> 0.085168461 | D39: =D38/D8 -> 0.11153522 | E39: =E38/E8 -> 0.10123923 | F39: =F38/F8 -> 0.081777186 | G39: =AVERAGE(B39:F39) -> 0.091638823 | H39: =AVERAGE(C39:G39) -> 0.094271785
A41: =A12 -> Mining Royalty | B41: =B12 -> 2759 | C41: =C12 -> 3667 | D41: =D12 -> 4068 | E41: =E12 -> 3517 | F41: =F12 -> 4103 | G41: =G42*G8 -> 487.00446 | H41: =H42*H8 -> 7799.6763
A42: % of Net Revenue | B42: =B41/B8 -> 0.12500566 | C42: =C41/C8 -> 0.12737061 | D42: =D41/D8 -> 0.12226497 | E42: =E41/E8 -> 0.12524037 | F42: =F41/F8 -> 0.12417905 | G42: =AVERAGE(B42:F42) -> 0.12481213 | H42: =AVERAGE(C42:G42) -> 0.12477343
A44: =A13 -> Changes in inventories of finished goods | B44: =B13 -> 239 | C44: =C13 -> -278 | D44: =D13 -> -143 | E44: =E13 -> -157 | F44: =F13 -> -64 | G44: =G45*G8 -> -8.3134715 | H44: =H45*H8 -> -295.20583
A45: % of Net Revenue | B45: =B44/B8 -> 0.010828689 | C45: =C44/C8 -> -0.0096561306 | D45: =D44/D8 -> -0.0042979082 | E45: =E44/E8 -> -0.0055907699 | F45: =F44/F8 -> -0.0019369874 | G45: =AVERAGE(B45:F45) -> -0.0021306214 | H45: =AVERAGE(C45:G45) -> -0.0047224835
A47: =A17 -> Employee benefits expense | B47: =B17 -> 760 | C47: =C17 -> 718 | D47: =D17 -> 845 | E47: =E17 -> 828 | F47: =F17 -> 886 | G47: =G48*G8 -> 110.08861 | H47: =H48*H8 -> 1685.9177
A48: % of Net Revenue | B48: =B47/B8 -> 0.034434326 | C48: =C47/C8 -> 0.024939215 | D48: =D47/D8 -> 0.02539673 | E48: =E47/E8 -> 0.029485079 | F48: =F47/F8 -> 0.026815169 | G48: =AVERAGE(B48:F48) -> 0.028214104 | H48: =AVERAGE(C48:G48) -> 0.026970059
A50: =A18 -> Other expenses | B50: =B18 -> 5467 | C50: =C18 -> 6656 | D50: =D18 -> 8111 | E50: =E18 -> 8245 | F50: =F18 -> 9068 | G50: =G51*G8 -> 1007.2535 | H50: =H51*H8 -> 16267.36
A51: % of Net Revenue | B51: =B50/B8 -> 0.2477006 | C51: =C50/C8 -> 0.23119139 | D51: =D50/D8 -> 0.24377855 | E51: =E50/E8 -> 0.29360444 | F51: =F50/F8 -> 0.2744469 | G51: =AVERAGE(B51:F51) -> 0.25814438 | H51: =AVERAGE(C51:G51) -> 0.26023313

Sheet Balance sheet
A2: Hindustan Zinc | B2: 44286 | C2: 44651 | D2: 45016 | E2: 45382 | F2: 45747 | G2: 46112 | H2: 46477
A3: Balance Sheet | B3: Y | C3: Y | D3: Y | E3: Y | F3: Y | G3: Y | H3: Y
A4: (in INR Crores) | B4: Act | C4: Act | D4: Act | E4: Act | F4: Act | G4: Est | H4: Est
A6: ASSETS
A7: Non-current asset | K7: Always Forcast | M7: no forecast
A8: Property, plant and equipment | B8: 16447 | C8: 17165 | D8: 17530 | E8: 17971 | F8: 18485 | G8: ='Capex model'!G9 -> 18657.996 | H8: ='Capex model'!H9 -> 18743.794 | K8: most imp | L8: moderate imp | M8: Least imp
A9: Capital work-in-progress | B9: 1922 | C9: 2075 | D9: 2237 | E9: 1696 | F9: 2606 | G9: =F9 -> 2606 | H9: =G9 -> 2606 | K9: PPE | L9: CWIP | M9: All remaining items expect moderate & most
A10: Intangible Assets | B10: 361 | C10: 231 | D10: 92 | E10: 180 | F10: 123 | G10: =F10 -> 123 | H10: =G10 -> 123 | K10: Inventories | L10: Investments
A11: Financial assets | K11: Trade Rec | L11: Loan given
A12: Investments | B12: 0 | C12: 0 | D12: 257 | E12: 578 | F12: 823 | G12: =F12 -> 823 | H12: =G12 -> 823 | I12: based on news | K12: Other equity | L12: Equity Share Capital
A13: Loans | B13: 12 | C13: 2 | D13: 0 | E13: 0 | F13: 1 | G13: =F13 -> 1 | H13: =G13 -> 1 | I13: based on news | K13: Trade Payable | L13: Borrowoings & lease
A14: Others | B14: 43 | C14: 56 | D14: 112 | E14: 131 | F14: 95 | G14: =F14 -> 95 | H14: =G14 -> 95 | K14: Cash
A15: Deferred tax assets (net) | B15: 1058 | C15: 0 | D15: 0 | E15: 0 | F15: 0 | G15: =F15 -> 0 | H15: =G15 -> 0
A16: Other non-current assets | B16: 431 | C16: 275 | D16: 290 | E16: 569 | F16: 591 | G16: =F16 -> 591 | H16: =G16 -> 591
A17: Income tax assets | B17: 885 | C17: 884 | D17: 145 | E17: 145 | F17: 140 | G17: =F17 -> 140 | H17: =G17 -> 140 | L17: Most assets are in plant and machinery → shows a core operating business, not idle assets
A18: Total non-current assets | B18: =B8+B9+B10+B13+B14+B15+B16+B17 -> 21159 | C18: =C8+C9+C10+C12+C13+C14+C15+C16+C17 -> 20688 | D18: =D8+D9+D10+D12+D13+D14+D15+D16+D17 -> 20663 | E18: =E8+E9+E10+E12+E13+E14+E15+E16+E17 -> 21270 | F18: =F8+F9+F10+F12+F13+F14+F15+F16+F17 -> 22864 | G18: =G8+G9+G10+G12+G13+G14+G15+G16+G17 -> 23036.996 | H18: =H8+H9+H10+H12+H13+H14+H15+H16+H17 -> 23122.794 | L18: Cash and investments fluctuate → active cash management.
L19: Inventory levels look controlled → no sign of overstocking.
A20: current assets | L20: Equity is the main funding source → strong financial base.
A21: Inventories | B21: 1425 | C21: 1953 | D21: 1862 | E21: 1926 | F21: 1889 | G21: =G22*'P&L '!G10 -> 245.89193 | H21: =H22*'P&L '!H10 -> 3920.0046 | L21: Debt is present but reasonable → leverage is under control.
A22: % of COGS | B22: =B21/'P&L '!B10 -> 0.3012685 | C22: =C21/'P&L '!C10 -> 0.33436055 | D22: =D21/'P&L '!D10 -> 0.24384494 | E22: =E21/'P&L '!E10 -> 0.31049492 | F22: =F21/'P&L '!F10 -> 0.28022549 | G22: =AVERAGE(B22:F22) -> 0.29403888 | H22: =AVERAGE(C22:G22) -> 0.29259296 | L22: Current liabilities rise with operations → normal business growth pattern.
A23: Financial Assets | L23: Ongoing increase in fixed assets → company is expanding.
A24: Investments | B24: 12957 | C24: 15052 | D24: 9850 | E24: 9874 | F24: 9149 | G24: =F24 -> 9149 | H24: =G24 -> 9149 | I24: based on news | L24: Overall: Financial position looks stable, risk is moderate, and the structure supports future growth.
A25: Trade receivables | B25: 406 | C25: 716 | D25: 380 | E25: 155 | F25: 117 | G25: =G26*'P&L '!G8 -> 49.746529 | H25: =H26*'P&L '!H8 -> 726.38297
A26: % of Net Revenue | B26: =B25/'P&L '!B8 -> 0.018395179 | C26: =C25/'P&L '!C8 -> 0.024869746 | D26: =D25/'P&L '!D8 -> 0.011421015 | E26: =E25/'P&L '!E8 -> 0.0055195499 | F26: =F25/'P&L '!F8 -> 0.0035410551 | G26: =AVERAGE(B26:F26) -> 0.012749309 | H26: =AVERAGE(C26:G26) -> 0.011620135
A27: Cash and cash equivalents | B27: 313 | C27: 1592 | D27: 59 | E27: 53 | F27: 96 | G27: ='Cash flow'!G63 -> 96 | H27: ='Cash flow'!H63 -> 96
A28: Other Bank balances | B28: 9063 | C28: 4171 | D28: 1353 | E28: 122 | F28: 81 | G28: =F28 -> 81 | H28: =G28 -> 81
A29: Loans | B29: 2 | C29: 2 | D29: 3 | E29: 1 | F29: 1 | G29: =F29 -> 1 | H29: =G29 -> 1 | I29: based on news
A30: Others | B30: 53 | C30: 33 | D30: 89 | E30: 59 | F30: 41 | G30: =F30 -> 41 | H30: =G30 -> 41
A31: Income tax assets | B31: 0 | C31: 0 | D31: 872 | E31: 0 | F31: 1 | G31: =F31 -> 1 | H31: =G31 -> 1
A32: Other current assets | B32: 349 | C32: 463 | D32: 336 | E32: 435 | F32: 251 | G32: =F32 -> 251 | H32: =G32 -> 251
A33: Total current assets | B33: =B21+B24+B25+B27+B28+B29+B30+B32 -> 24568 | C33: =C21+C24+C25+C27+C28+C29+C30+C32 -> 23982 | D33: =D21+D24+D25+D27+D28+D29+D30+D31+D32 -> 14804 | E33: =E21+E24+E25+E27+E28+E29+E30+E31+E32 -> 12625 | F33: =F21+F24+F25+F27+F28+F29+F30+F31+F32 -> 11626 | G33: =G21+G24+G25+G27+G28+G29+G30+G31+G32 -> 9915.6385 | H33: =H21+H24+H25+H27+H28+H29+H30+H31+H32 -> 14266.388
A34: TOTAL | B34: =B18+B33 -> 45727 | C34: =C18+C33 -> 44670 | D34: =D18+D33 -> 35467 | E34: =E18+E33 -> 33895 | F34: =F18+F33 -> 34490 | G34: =G18+G33 -> 32952.634 | H34: =H18+H33 -> 37389.181
A36: EQUITY AND LIABILITES
A37: equity
A38: Equity share capital | B38: 845 | C38: 845 | D38: 845 | E38: 845 | F38: 845 | G38: =F38 -> 845 | H38: =G38 -> 845 | I38: based on news
A39: Other equity | B39: 31468 | C39: 33436 | D39: 12087 | E39: 14350 | F39: 12481 | G39: =F39+'P&L '!G34-'Ratio Analysis'!H8 -> 10974.065 | H39: =G39+'P&L '!H34-'Ratio Analysis'!I8 -> 31506.909 | I39: Last year other equity-current year profit-current year dividend
A40: Total equity | B40: =B38+B39 -> 32313 | C40: =C39+C38 -> 34281 | D40: =D38+D39 -> 12932 | E40: =E38+E39 -> 15195 | F40: =F38+F39 -> 13326 | G40: =G38+G39 -> 11819.065 | H40: =H38+H39 -> 32351.909
A42: Liabilities
A43: non-current liabilities
A44: Financial liabilities
A45: Borrowings | B45: 4312 | C45: 2111 | D45: 1500 | E45: 4246 | F45: 5990 | G45: =F45 -> 5990 | H45: =G45 -> 5990 | I45: based on news
A46: Lease Liabilities | B46: 0 | C46: 6 | D46: 19 | E46: 178 | F46: 178 | G46: =F46 -> 178 | H46: =G46 -> 178 | I46: based on news
A47: Other financial liabilities | B47: 8 | C47: 0 | D47: 0 | E47: 0 | F47: 342 | G47: =F47 -> 342 | H47: =G47 -> 342
A48: Other non-current liabilities | B48: 1036 | C48: 1024 | D48: 1060 | E48: 925 | F48: 963 | G48: =F48 -> 963 | H48: =G48 -> 963
A49: Provisions | B49: 182 | C49: 212 | D49: 189 | E49: 199 | F49: 200 | G49: =F49 -> 200 | H49: =G49 -> 200
A50: Deferred tax liabilities | B50: 0 | C50: 942 | D50: 2314 | E50: 2311 | F50: 2292 | G50: =F50 -> 2292 | H50: =G50 -> 2292
A51: Total non-current liabilities | B51: =B45+B47+B48+B49 -> 5538 | C51: =C45+C46+C47+C48+C49+C50 -> 4295 | D51: =D45+D46+D47+D48+D49+D50 -> 5082 | E51: =E45+E46+E47+E48+E49+E50 -> 7859 | F51: =F45+F46+F47+F48+F49+F50 -> 9965 | G51: =G45+G46+G47+G48+G49+G50 -> 9965 | H51: =H45+H46+H47+H48+H49+H50 -> 9965
A53: current liabilities
A54: Financial liabilities
A55: Lease Liabilities | B55: 0 | C55: 15 | D55: 21 | E55: 88 | F55: 138 | G55: =F55 -> 138 | H55: =G55 -> 138 | I55: based on news
A56: Borrowing | B56: 2161 | C56: 712 | D56: 10341 | E56: 4210 | F56: 4661 | G56: =F56 -> 4661 | H56: =G56 -> 4661 | I56: based on news
A57: Operational buyers' credit/ suppliers' credit | B57: 0 | C57: 280 | D57: 307 | E57: 399 | F57: 569 | G57: =F57 -> 569 | H57: =G57 -> 569
A58: Trade payables
A59: a) Total outstanding dues of Micro, Small and Medium Enterprises | B59: 38 | C59: 2038 | D59: 2088 | E59: 2106 | F59: 2204 | G59: =G60*('P&L '!G11+'P&L '!G12) -> 213.66757 | H59: =H60*('P&L '!H11+'P&L '!H12) -> 4133.7558
A60: % of purchases | B60: =B59/('P&L '!B11+'P&L '!B12) -> 0.0084613672 | C60: =C59/('P&L '!C11+'P&L '!C12) -> 0.33306096 | D60: =D59/('P&L '!D11+'P&L '!D12) -> 0.26841496 | E60: =E59/('P&L '!E11+'P&L '!E12) -> 0.33113208 | F60: =F59/('P&L '!F11+'P&L '!F12) -> 0.3238795 | G60: =AVERAGE(B60:F60) -> 0.25298977 | H60: =AVERAGE(C60:G60) -> 0.30189545
A61: b) Total outstanding dues to creditors other than Micro | B61: 1507 | C61: 0 | D61: 0 | E61: 0 | F61: 0 | G61: =G62*('P&L '!G11+'P&L '!G12) -> 56.680782 | H61: =H62*('P&L '!H11+'P&L '!H12) -> 183.78854
A62: % of purchases | B62: =B61/('P&L '!B11+'P&L '!B12) -> 0.33556001 | C62: =C61/('P&L '!C11+'P&L '!C12) -> 0 | D62: =D61/('P&L '!D11+'P&L '!D12) -> 0 | E62: =E61/('P&L '!E11+'P&L '!E12) -> 0 | F62: =F61/('P&L '!F11+'P&L '!F12) -> 0 | G62: =AVERAGE(B62:F62) -> 0.067112002 | H62: =AVERAGE(C62:G62) -> 0.0134224
A63: Other financial liabilities | B63: 1971 | C63: 1901 | D63: 2419 | E63: 1414 | F63: 1717 | G63: =F63 -> 1717 | H63: =G63 -> 1717
A64: Other current liabilities | B64: 1947 | C64: 860 | D64: 1687 | E64: 2126 | F64: 1579 | G64: =F64 -> 1579 | H64: =G64 -> 1579
A65: Income tax liabilities | B65: 0 | C65: 256 | D65: 564 | E65: 477 | F65: 0 | G65: =F65 -> 0 | H65: =G65 -> 0
A66: Provisions | B66: 70 | C66: 32 | D66: 26 | E66: 21 | F66: 19 | G66: =F66 -> 19 | H66: =G66 -> 19
A67: Current tax liabilities | B67: 182 | C67: 0 | D67: 0 | E67: 0 | F67: 312 | G67: =F67 -> 312 | H67: =G67 -> 312
A68: Total current liabilities | B68: =B56+B57+B59+B61+B63+B64+B66+B67 -> 7876 | C68: =C55+C56+C57+C59+C61+C63+C64+C65+C66+C67 -> 6094 | D68: =D55+D56+D57+D59+D61+D63+D64+D65+D66+D67 -> 17453 | E68: =E55+E56+E57+E59+E61+E63+E64+E65+E66+E67 -> 10841 | F68: =F55+F56+F57+F59+F61+F63+F64+F65+F66+F67 -> 11199 | G68: =G55+G56+G57+G59+G61+G63+G64+G65+G66+G67 -> 9265.3484 | H68: =H55+H56+H57+H59+H61+H63+H64+H65+H66+H67 -> 13312.544
A69: TOTAL | B69: =B40+B51+B68 -> 45727 | C69: =C40+C51+C68 -> 44670 | D69: =D40+D51+D68 -> 35467 | E69: =E51+E68+E40 -> 33895 | F69: =F51+F68+F40 -> 34490 | G69: =G51+G68+G40 -> 31049.414 | H69: =H51+H68+H40 -> 55629.453
A71: Reconcillation | B71: =B34-B69 -> 0 | C71: =C34-C69 -> 0 | D71: =D34-D69 -> 0 | E71: =E34-E69 -> 0 | F71: =F34-F69 -> 0 | G71: =G34-G69 -> 1903.2207 | H71: 1899.02
A74: CALCULATIONS OF CHANGES IN WORKING CAPITAL
A75: WORKING CAPITAL ADJ FOR CASH | B75: =B33-B68-B27-B28 -> 7316 | C75: =C33-C68-C27-C28 -> 12125 | D75: =D33-D68-D27-D28 -> -4061 | E75: =E33-E68-E27-E28 -> 1609 | F75: =F33-F68-F27-F28 -> 250 | G75: =G33-G68-G27-G28 -> 473.29011 | H75: =H33-H68-H27-H28 -> 776.84324 | I75: CA-CL-CASH-BANK
A76: CHANGES IN WC | C76: =C75-B75 -> 4809 | D76: =D75-C75 -> -16186 | E76: =E75-D75 -> 5670 | F76: =F75-E75 -> -1359 | G76: =G75-F75 -> 223.29011 | H76: =H75-G75 -> 303.55313 | I76: NEW-OLD

Sheet Cash flow
A1: Hindustan Zinc | B1: 44286 | C1: 44651 | D1: 45016 | E1: 45382 | F1: 45747 | G1: 46112 | H1: 46477
A2: Cash Flow Statement | B2: Y | C2: Y | D2: Y | E2: Y | F2: Y | G2: Y | H2: Y
A3: (in INR Crores) | B3: Act | C3: Act | D3: Act | E3: Act | F3: Act | G3: Est | H3: Est
A5: Cash Flow From Operating Activities
A6: Net profit before tax | B6: 10574 | C6: 14100 | D6: 15288 | E6: 10307 | F6: 13553 | G6: ='P&L '!G29 -> -1915.6506 | H6: ='P&L '!H29 -> 26785.505 | J6: Operating Cash Flow
A7: Adjustments to reconcile profit to net cash | J7: Positive in most years → core business generates real cash.
A8: Depreciation and amortization expense | B8: 2531 | C8: 2917 | D8: 3264 | E8: 3468 | F8: 3640 | G8: ='P&L '!G23 -> 4103.6177 | H8: ='P&L '!H23 -> 4512.8743 | J8: Moves in line with profits → earnings quality looks reliable.
A9: Exceptional item | B9: 0 | C9: 0 | D9: 0 | E9: 0 | F9: 56 | G9: ='P&L '!G25 -> -1040.5552 | H9: ='P&L '!H25 -> 27704.822 | J9: Some fluctuations → working capital changes affecting cash timing.
A10: Interest expense | B10: 386 | C10: 290 | D10: 333 | E10: 955 | F10: 1095 | G10: ='P&L '!G26 -> 0 | H10: ='P&L '!H26 -> 0
A11: Interest income | B11: -941 | C11: -838 | D11: -1154 | E11: -761 | F11: -705 | G11: ='P&L '!G27 -> 875.09541 | H11: ='P&L '!H27 -> 919.31697
A12: Amortization of deferred revenue | B12: -120 | C12: -135 | D12: -157 | E12: -179 | F12: -176 | G12: ='P&L '!G29 -> -1915.6506 | H12: ='P&L '!H29 -> 26785.505
A13: Allowance for impairment loss on financial assets | B13: 0 | C13: 0 | D13: 0 | E13: 0 | F13: 0 | G13: ='P&L '!G30 -> 0 | H13: ='P&L '!H30 -> 0
A14: Provision for doubtful debts/ advance | B14: 0 | C14: 0 | D14: 28 | E14: 0 | F14: 0 | G14: ='P&L '!G31 -> -408.71608 | H14: ='P&L '!H31 -> 6194.0926
A15: Net Loss on investments measured at FVTPL | B15: 0 | C15: 28 | D15: 16 | E15: -64 | F15: 0 | G15: ='P&L '!G32 -> 0.21335628 | H15: ='P&L '!H32 -> 0.23124793
A16: Net (Gain)/Loss on foreign exchange | B16: 0 | C16: 0 | D16: 0 | E16: -13 | F16: 43 | G16: ='P&L '!G33 -> 0 | H16: ='P&L '!H33 -> 0
A17: Net gain on investments measured at FVTPL | B17: -400 | C17: 0 | D17: 0 | E17: 0 | F17: 28 | G17: ='P&L '!G34 -> -1506.9346 | H17: ='P&L '!H34 -> 20591.413
A18: Net (Gain)/Loss on sale of Property, Plant and Equipment | B18: -42 | C18: -11 | D18: 9 | E18: 20 | F18: 9 | G18: ='P&L '!G35 -> 0 | H18: ='P&L '!H35 -> 0
A19: Net (Gain) on sale of financial asset investments | B19: -304 | C19: -205 | D19: -32 | E19: -37 | F19: -63 | G19: ='P&L '!G36 -> 0 | H19: ='P&L '!H36 -> 0
A20: Charge pertaining to Amnesty Scheme | B20: 0 | C20: 134 | D20: 0 | E20: 0 | F20: 0 | G20: ='P&L '!G37 -> 0 | H20: ='P&L '!H37 -> 0
A21: Transfer of CSR Assets | B21: 0 | C21: 0 | D21: 117 | E21: 0 | F21: 0 | G21: ='P&L '!G38 -> 357.56552 | H21: ='P&L '!H38 -> 5892.9968
A22: operating profit before working capital changes | B22: =B6+B8+B10+B11+B12+B17+B18+B19 -> 11684 | C22: =C6+C8+C10+C11+C12+C17+C18+C19 -> 16118 | D22: =D6+D8+D10+D11+D12+D17+D18+D19 -> 17551 | E22: =E6+E8+E10+E11+E12+E17+E18+E19 -> 13773 | F22: =F6+F8+F10+F11+F12+F17+F18+F19 -> 17381 | G22: =G6+G8+G10+G11+G12+G17+G18+G19 -> -359.52275 | H22: =H6+H8+H10+H11+H12+H17+H18+H19 -> 79594.615
A24: changes in assets and liabilities
A25: Increase)/Decrease in Inventories | B25: 411 | C25: -528 | D25: 91 | E25: -64 | F25: 37 | G25: ='Balance sheet'!F21-'Balance sheet'!G21 -> 1643.1081 | H25: ='Balance sheet'!G21-'Balance sheet'!H21 -> -3674.1127
A26: (Increase)/Decrease in Trade receivables | B26: -26 | C26: -310 | D26: 336 | E26: 225 | F26: 38 | G26: ='Balance sheet'!F25-'Balance sheet'!G25 -> 67.253471 | H26: ='Balance sheet'!G25-'Balance sheet'!H25 -> -676.63644
A27: (Increase)/Decrease in Other current assets | B27: -52 | C27: -94 | D27: 42 | E27: -66 | F27: 212 | G27: ='Balance sheet'!F28-'Balance sheet'!G28+'Balance sheet'!F30-'Balance sheet'!G30+'Balance sheet'!F31-'Balance sheet'!G31+'Balance sheet'!F32-'Balance sheet'!G32 -> 0 | H27: ='Balance sheet'!G28-'Balance sheet'!H28+'Balance sheet'!G30-'Balance sheet'!H30+'Balance sheet'!G31-'Balance sheet'!H31+'Balance sheet'!G32-'Balance sheet'!H32 -> 0
A28: (Increase)/Decrease in Other non current assets | B28: 12 | C28: 4 | D28: -57 | E28: -3 | F28: -91 | G28: ='Balance sheet'!F10-'Balance sheet'!G10+'Balance sheet'!F14-'Balance sheet'!G14+'Balance sheet'!F15-'Balance sheet'!G15+'Balance sheet'!G16-'Balance sheet'!F16+'Balance sheet'!F17-'Balance sheet'!G17 -> 0 | H28: ='Balance sheet'!G10-'Balance sheet'!H10+'Balance sheet'!G14-'Balance sheet'!H14+'Balance sheet'!G15-'Balance sheet'!H15+'Balance sheet'!H16-'Balance sheet'!G16+'Balance sheet'!G17-'Balance sheet'!H17 -> 0
A29: (Increase/(Decrease) in Trade payables | B29: 58 | C29: 773 | D29: 77 | E29: 109 | F29: 269 | G29: ='Balance sheet'!G59-'Balance sheet'!F59+'Balance sheet'!G61-'Balance sheet'!F61 -> -1933.6516 | H29: ='Balance sheet'!H59-'Balance sheet'!G59+'Balance sheet'!H61-'Balance sheet'!G61 -> 4047.196
A30: (Increase/(Decrease) in Other current liabilities | B30: 235 | C30: -1043 | D30: 68 | E30: 1206 | F30: -400 | G30: ='Balance sheet'!G60-'Balance sheet'!F60+'Balance sheet'!G62-'Balance sheet'!F62 -> -0.0037777258 | H30: ='Balance sheet'!H60-'Balance sheet'!G60+'Balance sheet'!H62-'Balance sheet'!G62 -> -0.0047839203
A31: (Increase/(Decrease) in non current liabilities | B31: 0 | C31: 0 | D31: 0 | E31: 0 | F31: 0 | G31: ='Balance sheet'!G61-'Balance sheet'!F61+'Balance sheet'!G63-'Balance sheet'!F63 -> 56.680782 | H31: ='Balance sheet'!H61-'Balance sheet'!G61+'Balance sheet'!H63-'Balance sheet'!G63 -> 127.10776
A32: cash flows from operations | B32: =B22+B25+B26+B27+B28+B29+B30+B31 -> 12322 | C32: =C22+C25+C26+C27+C28+C29+C30+C31 -> 14920 | D32: =D22+D25+D26+D27+D28+D29+D30+D31 -> 18108 | E32: =E22+E25+E26+E27+E28+E29+E30+E31 -> 15180 | F32: =F22+F25+F26+F27+F28+F29+F30+F31 -> 17446 | G32: =G22+G25+G26+G27+G28+G29+G30+G31 -> -526.13586 | H32: =H22+H25+H26+H27+H28+H29+H30+H31 -> 79418.164
A33: Income taxes paid during the year | B33: 1755 | C33: -2391 | D33: -3140 | E33: -1757 | F33: -3385 | G33: ='P&L '!G31 -> -408.71608 | H33: ='P&L '!H31 -> 6194.0926
A34: net cash flows from operating activities | B34: =B32-B33 -> 10567 | C34: =C32-C33 -> 17311 | D34: =D32-D33 -> 21248 | E34: =E32-E33 -> 16937 | F34: =F32-F33 -> 20831 | G34: =G32-G33 -> -117.41977 | H34: =H32-H33 -> 73224.072
A36: Cash Flow From Investing Activities | J36: Investing Cash Flow
A37: Purchases of Property, Plant and Equipment | B37: -2481 | C37: -2998 | D37: -3561 | E37: -3866 | F37: -4006 | G37: ='Capex model'!F6-'Capex model'!G6 -> -4276.6137 | H37: ='Capex model'!G6-'Capex model'!H6 -> -4598.6721 | J37: Mostly negative → company is investing in assets and expansion.
A38: Interest received | B38: 1507 | C38: 936 | D38: 1438 | E38: 538 | F38: 663 | G38: ='Capex model'!F7-'Capex model'!G7 -> -0.00096527018 | H38: ='Capex model'!G7-'Capex model'!H7 -> 0.0015875431 | J38: Large outflows for plant and equipment → growth strategy in action.
A39: Deposits made during the year | B39: -9952 | C39: -5500 | D39: -1500 | E39: 4 | F39: -984 | G39: ='Capex model'!F8-'Capex model'!G8 -> -4103.6177 | H39: ='Capex model'!G8-'Capex model'!H8 -> -4512.8743 | J39: Occasional inflows from asset sales → asset optimization.
A40: Deposits matured during the year | B40: 1244 | C40: 10227 | D40: 5500 | E40: -92 | F40: 1022 | G40: ='Capex model'!F9-'Capex model'!G9 -> -172.99602 | H40: ='Capex model'!G9-'Capex model'!H9 -> -85.797722
A41: Purchase of Non current investments | B41: 0 | C41: 0 | D41: -105 | E41: -306 | F41: -230 | G41: ='Capex model'!F10-'Capex model'!G10 -> 0 | H41: ='Capex model'!G10-'Capex model'!H10 -> 0
A42: Purchase of current investments | B42: -41385 | C42: -46753 | D42: -43187 | E42: -23242 | F42: -23902 | G42: ='Capex model'!F11-'Capex model'!G11 -> 0 | H42: ='Capex model'!G11-'Capex model'!H11 -> 0
A43: Proceeds from sale of current investments | B43: 48578 | C43: 44904 | D43: 47958 | E43: 23507 | F43: 24724 | G43: ='Capex model'!F12-'Capex model'!G12 -> 0 | H43: ='Capex model'!G12-'Capex model'!H12 -> 0
A44: Proceeds from sale of Property, Plant and Equipment | B44: 54 | C44: 30 | D44: 19 | E44: 51 | F44: 7 | G44: ='Capex model'!F13-'Capex model'!G13 -> 0 | H44: ='Capex model'!G13-'Capex model'!H13 -> 0
A45: Others | B45: 0 | C45: 0 | D45: 0 | E45: 0 | F45: 0 | G45: ='Balance sheet'!G9-'Balance sheet'!F9 -> 0 | H45: ='Capex model'!G14-'Capex model'!H14 -> 0
A46: net cash flows (used) in investing activities | B46: =B37+B38+B39+B40+B42+B43+B44 -> -2435 | C46: =C37+C38+C39+C40+C41+C42+C43+C44 -> 846 | D46: =D37+D38+D39+D40+D41+D42+D43+D44 -> 6562 | E46: =E37+E38+E39+E40+E41+E42+E43+E44 -> -3406 | F46: =F37+F38+F39+F40+F41+F42+F43+F44 -> -2706 | G46: =G37+G38+G39+G40+G41+G42+G43+G44 -> -8553.2283 | H46: =H37+H38+H39+H40+H41+H42+H43+H44 -> -9197.3426
A48: Cash Flow From Financing Activities | J48: Financing Cash Flow
A49: Interest and other finance charges paid | B49: -244 | C49: -332 | D49: -287 | E49: -1028 | F49: -1209 | G49: ='Balance sheet'!G40-'Balance sheet'!F40+'Balance sheet'!G49-'Balance sheet'!F49 -> -1506.9346 | H49: ='Balance sheet'!H40-'Balance sheet'!G40+'Balance sheet'!H49-'Balance sheet'!G49 -> 20528.643 | J49: Mixed trend → company both borrows and repays depending on need.
A50: Proceeds from short term borrowing | B50: 13473 | C50: 9 | D50: 13458 | E50: 6620 | F50: 9965 | G50: ='Balance sheet'!G41-'Balance sheet'!F41+'Balance sheet'!G50-'Balance sheet'!F50 -> 0 | H50: ='Balance sheet'!H41-'Balance sheet'!G41+'Balance sheet'!H50-'Balance sheet'!G50 -> 0 | J50: Dividend payments visible → strong enough cash position to reward shareholders
A51: Repayment of short term borrowings | B51: -11965 | C51: -2120 | D51: -5276 | E51: -13307 | F51: -9536 | G51: ='Balance sheet'!G42-'Balance sheet'!F42+'Balance sheet'!G51-'Balance sheet'!F51 -> 0 | H51: ='Balance sheet'!H42-'Balance sheet'!G42+'Balance sheet'!H51-'Balance sheet'!G51 -> 0 | J51: No aggressive borrowing spikes → financial discipline.
A52: Proceeds from working capital loan | B52: 0 | C52: 0 | D52: 0 | E52: 8 | F52: -8 | G52: ='Balance sheet'!G43-'Balance sheet'!F43+'Balance sheet'!G52-'Balance sheet'!F52 -> 0 | H52: ='Balance sheet'!H43-'Balance sheet'!G43+'Balance sheet'!H52-'Balance sheet'!G52 -> 0
A53: Proceeds from long term borrowings | B53: 5016 | C53: 0 | D53: 1500 | E53: 5442 | F53: 4547 | G53: ='Balance sheet'!G44-'Balance sheet'!F44+'Balance sheet'!G53-'Balance sheet'!F53 -> 0 | H53: ='Balance sheet'!H44-'Balance sheet'!G44+'Balance sheet'!H53-'Balance sheet'!G53 -> 0
A54: Repayment of long term borrowings | B54: 0 | C54: -2204 | D54: -704 | E54: -2112 | F54: -2783 | G54: ='Balance sheet'!G45-'Balance sheet'!F45+'Balance sheet'!G54-'Balance sheet'!F54 -> 0 | H54: ='Balance sheet'!H45-'Balance sheet'!G45+'Balance sheet'!H54-'Balance sheet'!G54 -> 0
A55: Payment of principal portion of lease liabilities | B55: -5 | C55: -5 | D55: -14 | E55: -76 | F55: -106 | G55: ='Balance sheet'!G46-'Balance sheet'!F46+'Balance sheet'!G55-'Balance sheet'!F55 -> 0 | H55: ='Balance sheet'!H46-'Balance sheet'!G46+'Balance sheet'!H55-'Balance sheet'!G55 -> 0
A56: Interest payment of lease liabilities | B56: 0 | C56: 0 | D56: 0 | E56: 0 | F56: -12253 | G56: ='Balance sheet'!G47-'Balance sheet'!F47+'Balance sheet'!G56-'Balance sheet'!F56 -> 0 | H56: ='Balance sheet'!H47-'Balance sheet'!G47+'Balance sheet'!H56-'Balance sheet'!G56 -> 0
A57: Loan given others | B57: 0 | C57: 0 | D57: 0 | E57: 0 | F57: 0 | G57: ='Balance sheet'!F13-'Balance sheet'!G13+'Balance sheet'!F29-'Balance sheet'!G29 -> 0 | H57: ='Balance sheet'!G13-'Balance sheet'!H13+'Balance sheet'!G29-'Balance sheet'!H29 -> 0
A58: Dividend paid | B58: -15972 | C58: -7606 | D58: -31901 | E58: -5493 | F58: -28 | G58: =-'Ratio Analysis'!H8 -> 0 | H58: =-'Ratio Analysis'!I8 -> -62.769658
A59: Borrowings paid | B59: 0 | C59: 0 | D59: 0 | E59: 0 | F59: 0 | G59: ='Balance sheet'!G45-'Balance sheet'!F45+'Balance sheet'!G56-'Balance sheet'!F56 -> 0 | H59: ='Balance sheet'!H45-'Balance sheet'!G45+'Balance sheet'!H56-'Balance sheet'!G56 -> 0
A60: Others | B60: 0 | C60: 0 | D60: ='Balance sheet'!D38-'Balance sheet'!C38 -> 0 | E60: ='Balance sheet'!E38-'Balance sheet'!D38 -> 0 | F60: ='Balance sheet'!F38-'Balance sheet'!E38 -> 0 | G60: ='Balance sheet'!G38-'Balance sheet'!F38 -> 0 | H60: ='Balance sheet'!H38-'Balance sheet'!G38 -> 0
A61: net cash flows (used) in financing activities | B61: =B49+B50+B51+B53+B55+B58 -> -9697 | C61: =C49+C50+C51+C53+C55+C58 -> -10054 | D61: =D49+D50+D51+D53+D55+D58 -> -22520 | E61: =E49+E50+E51+E53+E55+E58 -> -7842 | F61: =F49+F50+F51+F53+F55+F58 -> 3633 | G61: =G49+G50+G51+G53+G55+G58 -> -1506.9346 | H61: =H49+H50+H51+H53+H55+H58 -> 20465.873 | J61: Net Cash Position
A62: Net increase /(decrease) in Cash and cash equivalents | B62: -1565 | C62: 1279 | D62: -1533 | E62: -6 | F62: 43 | G62: 0 | H62: 0 | J62: Cash balance fluctuates but stays positive → liquidity not under stress.
A63: Cash and cash equivalents at the beginning of the year | B63: 1878 | C63: 313 | D63: 1592 | E63: 59 | F63: 53 | G63: =F64 -> 96 | H63: =G64 -> 96 | J63: Years with negative net change mostly due to heavy investments, not losses.
A64: Cash and cash equivalents at the end of the year | B64: =B62+B63 -> 313 | C64: =C62+C63 -> 1592 | D64: =D62+D63 -> 59 | E64: =E62+E63 -> 53 | F64: =F62+F63 -> 96 | G64: =G62+G63 -> 96 | H64: =H62+H63 -> 96

Sheet Common Size  P&L
A3: Hindustan Zinc | B3: 44286 | C3: 44651 | D3: 45016 | E3: 45382 | F3: 45747 | G3: 46112 | H3: 46477
A4: Common Size P&L | B4: Y | C4: Y | D4: Y | E4: Y | F4: Y | G4: Y | H4: Y
A5: (in INR Crores) | B5: Act | C5: Act | D5: Act | E5: Act | F5: Act | G5: Est | H5: Est
A7: Revenue from operations | B7: ='P&L '!B6/'P&L '!$B$8 -> 1 | C7: ='P&L '!C6/'P&L '!$C$8 -> 1 | D7: ='P&L '!D6/'P&L '!$D$8 -> 1 | E7: ='P&L '!E6/'P&L '!$E$8 -> 1 | F7: ='P&L '!F6/'P&L '!$F$8 -> 1 | G7: ='P&L '!G6/'P&L '!$G$8 -> 1 | H7: ='P&L '!H6/'P&L '!$H$8 -> 1 | J7: Cost structure is stable with consistent COGS percentage, showing operational control.
A8: Excise duty | B8: ='P&L '!B7/'P&L '!$B$8 -> 0 | C8: ='P&L '!C7/'P&L '!$C$8 -> 0 | D8: ='P&L '!D7/'P&L '!$D$8 -> 0 | E8: ='P&L '!E7/'P&L '!$E$8 -> 0 | F8: ='P&L '!F7/'P&L '!$F$8 -> 0 | G8: ='P&L '!G7/'P&L '!$G$8 -> 0 | H8: ='P&L '!H7/'P&L '!$H$8 -> 0 | J8: Margins remain strong overall, though they fluctuate with revenue cycles.
A9: Net Revenue | B9: ='P&L '!B8/'P&L '!$B$8 -> 1 | C9: ='P&L '!C8/'P&L '!$C$8 -> 1 | D9: ='P&L '!D8/'P&L '!$D$8 -> 1 | E9: ='P&L '!E8/'P&L '!$E$8 -> 1 | F9: ='P&L '!F8/'P&L '!$F$8 -> 1 | G9: ='P&L '!G8/'P&L '!$G$8 -> 1 | H9: ='P&L '!H8/'P&L '!$H$8 -> 1 | J9: Operating expenses are low and stable, indicating efficient cost management.
J10: Profitability mainly depends on sales performance and commodity price movements.
A11: Cost of Goods Sold | B11: ='P&L '!B10/'P&L '!$B$8 -> 0.21430837 | C11: ='P&L '!C10/'P&L '!$C$8 -> 0.20288295 | D11: ='P&L '!D10/'P&L '!$D$8 -> 0.22950228 | E11: ='P&L '!E10/'P&L '!$E$8 -> 0.22088883 | F11: ='P&L '!F10/'P&L '!$F$8 -> 0.20401925 | G11: ='P&L '!G10/'P&L '!$G$8 -> 0.21432033 | H11: ='P&L '!H10/'P&L '!$H$8 -> 0.21432273
A12: Power and fuel | B12: ='P&L '!B11/'P&L '!$B$8 -> 0.078474016 | C12: ='P&L '!C11/'P&L '!$C$8 -> 0.085168461 | D12: ='P&L '!D11/'P&L '!$D$8 -> 0.11153522 | E12: ='P&L '!E11/'P&L '!$E$8 -> 0.10123923 | F12: ='P&L '!F11/'P&L '!$F$8 -> 0.081777186 | G12: ='P&L '!G11/'P&L '!$G$8 -> 0.091638823 | H12: ='P&L '!H11/'P&L '!$H$8 -> 0.094271785
A13: Mining Royalty | B13: ='P&L '!B12/'P&L '!$B$8 -> 0.12500566 | C13: ='P&L '!C12/'P&L '!$C$8 -> 0.12737061 | D13: ='P&L '!D12/'P&L '!$D$8 -> 0.12226497 | E13: ='P&L '!E12/'P&L '!$E$8 -> 0.12524037 | F13: ='P&L '!F12/'P&L '!$F$8 -> 0.12417905 | G13: ='P&L '!G12/'P&L '!$G$8 -> 0.12481213 | H13: ='P&L '!H12/'P&L '!$H$8 -> 0.12477343
A14: Changes in inventories of finished goods | B14: ='P&L '!B13/'P&L '!$B$8 -> 0.010828689 | C14: ='P&L '!C13/'P&L '!$C$8 -> -0.0096561306 | D14: ='P&L '!D13/'P&L '!$D$8 -> -0.0042979082 | E14: ='P&L '!E13/'P&L '!$E$8 -> -0.0055907699 | F14: ='P&L '!F13/'P&L '!$F$8 -> -0.0019369874 | G14: ='P&L '!G13/'P&L '!$G$8 -> -0.0021306214 | H14: ='P&L '!H13/'P&L '!$H$8 -> -0.0047224835
A15: Gross Profit | B15: ='P&L '!B14/'P&L '!$B$8 -> 1 | C15: ='P&L '!C14/'P&L '!$C$8 -> 0.79711705 | D15: ='P&L '!D14/'P&L '!$D$8 -> 0.77049772 | E15: ='P&L '!E14/'P&L '!$E$8 -> 0.77911117 | F15: ='P&L '!F14/'P&L '!$F$8 -> 0.79598075 | G15: ='P&L '!G14/'P&L '!$G$8 -> 0.78567967 | H15: ='P&L '!H14/'P&L '!$H$8 -> 0.78567727
A17: Selling & General Adm Expenses | B17: ='P&L '!B16/'P&L '!$B$8 -> 0 | C17: ='P&L '!C16/'P&L '!$C$8 -> 0 | D17: ='P&L '!D16/'P&L '!$D$8 -> 0 | E17: ='P&L '!E16/'P&L '!$E$8 -> 0 | F17: ='P&L '!F16/'P&L '!$F$8 -> 0 | G17: ='P&L '!G16/'P&L '!$G$8 -> 0 | H17: ='P&L '!H16/'P&L '!$H$8 -> 0
A18: Employee benefits expense | B18: ='P&L '!B17/'P&L '!$B$8 -> 0.034434326 | C18: ='P&L '!C17/'P&L '!$C$8 -> 0.024939215 | D18: ='P&L '!D17/'P&L '!$D$8 -> 0.02539673 | E18: ='P&L '!E17/'P&L '!$E$8 -> 0.029485079 | F18: ='P&L '!F17/'P&L '!$F$8 -> 0.026815169 | G18: ='P&L '!G17/'P&L '!$G$8 -> 0.028214104 | H18: ='P&L '!H17/'P&L '!$H$8 -> 0.026970059
A19: Other expenses | B19: ='P&L '!B18/'P&L '!$B$8 -> 0.2477006 | C19: ='P&L '!C18/'P&L '!$C$8 -> 0.23119139 | D19: ='P&L '!D18/'P&L '!$D$8 -> 0.24377855 | E19: ='P&L '!E18/'P&L '!$E$8 -> 0.29360444 | F19: ='P&L '!F18/'P&L '!$F$8 -> 0.2744469 | G19: ='P&L '!G18/'P&L '!$G$8 -> 0.25814438 | H19: ='P&L '!H18/'P&L '!$H$8 -> 0.26023313
A20: EBITDA | B20: ='P&L '!B19/'P&L '!$B$8 -> 0.71786507 | C20: ='P&L '!C19/'P&L '!$C$8 -> 0.54098645 | D20: ='P&L '!D19/'P&L '!$D$8 -> 0.50132243 | E20: ='P&L '!E19/'P&L '!$E$8 -> 0.45602165 | F20: ='P&L '!F19/'P&L '!$F$8 -> 0.49471868 | G20: ='P&L '!G19/'P&L '!$G$8 -> 0.49932118 | H20: ='P&L '!H19/'P&L '!$H$8 -> 0.49847408
A22: Other income | B22: ='P&L '!B21/'P&L '!$B$8 -> 0.08241584 | C22: ='P&L '!C21/'P&L '!$C$8 -> 0.042236888 | D22: ='P&L '!D21/'P&L '!$D$8 -> 0.041446261 | E22: ='P&L '!E21/'P&L '!$E$8 -> 0.038245139 | F22: ='P&L '!F21/'P&L '!$F$8 -> 0.029750916 | G22: ='P&L '!G21/'P&L '!$G$8 -> 0.28569699 | H22: ='P&L '!H21/'P&L '!$H$8 -> 0.016920693
A23: Depreciation and amortization expense | B23: ='P&L '!B23/'P&L '!$B$8 -> 0.11467537 | C23: ='P&L '!C23/'P&L '!$C$8 -> 0.1012157 | D23: ='P&L '!D23/'P&L '!$D$8 -> 0.098100505 | E23: ='P&L '!E23/'P&L '!$E$8 -> 0.12349548 | F23: ='P&L '!F23/'P&L '!$F$8 -> 0.11016616 | G23: ='P&L '!G22/'P&L '!$G$8 -> 2.8649919e-05 | H23: ='P&L '!H22/'P&L '!$H$8 -> 1.6968204e-06
A24: EBIT | B24: ='P&L '!B25/'P&L '!$B$8 -> 0.68560555 | C24: ='P&L '!C25/'P&L '!$C$8 -> 0.48200764 | D24: ='P&L '!D25/'P&L '!$D$8 -> 0.44466819 | E24: ='P&L '!E25/'P&L '!$E$8 -> 0.37077131 | F24: ='P&L '!F25/'P&L '!$F$8 -> 0.41430344 | G24: ='P&L '!G23/'P&L '!$G$8 -> 1.0516973 | H24: ='P&L '!H23/'P&L '!$H$8 -> 0.072193611
A26: Finance costs | B26: ='P&L '!B27/'P&L '!$B$8 -> 0.017489013 | C26: ='P&L '!C27/'P&L '!$C$8 -> 0.010072942 | D26: ='P&L '!D27/'P&L '!$D$8 -> 0.010008415 | E26: ='P&L '!E27/'P&L '!$E$8 -> 0.034007549 | F26: ='P&L '!F27/'P&L '!$F$8 -> 0.033140643 | G26: ='P&L '!G25/'P&L '!$G$8 -> -0.26667911 | H26: ='P&L '!H25/'P&L '!$H$8 -> 0.44320116
A27: PBT | B27: ='P&L '!B29/'P&L '!$B$8 -> 0.66811653 | C27: ='P&L '!C29/'P&L '!$C$8 -> 0.4719347 | D27: ='P&L '!D29/'P&L '!$D$8 -> 0.43465977 | E27: ='P&L '!E29/'P&L '!$E$8 -> 0.33676376 | F27: ='P&L '!F29/'P&L '!$F$8 -> 0.3811628 | G27: ='P&L '!G26/'P&L '!$G$8 -> 0 | H27: ='P&L '!H26/'P&L '!$H$8 -> 0
A29: Current tax | B29: ='P&L '!B31/'P&L '!$B$8 -> 0.082778306 | C29: ='P&L '!C31/'P&L '!$C$8 -> 0.084925321 | D29: ='P&L '!D31/'P&L '!$D$8 -> 0.10311974 | E29: ='P&L '!E31/'P&L '!$E$8 -> 0.090769888 | F29: ='P&L '!F31/'P&L '!$F$8 -> 0.09763627 | G29: ='P&L '!G28/'P&L '!$G$8 -> 2.0449911e-05 | H29: ='P&L '!H28/'P&L '!$H$8 -> 1.340982e-06
A30: Deferred tax | B30: ='P&L '!B33/'P&L '!$B$8 -> 0.034751484 | C30: ='P&L '!C33/'P&L '!$C$8 -> 0.070371657 | D30: ='P&L '!D33/'P&L '!$D$8 -> 0.040454436 | E30: ='P&L '!E33/'P&L '!$E$8 -> -3.5609999e-05 | F30: ='P&L '!F33/'P&L '!$F$8 -> -0.00078690112 | G30: ='P&L '!G29/'P&L '!$G$8 -> -0.49095329 | H30: ='P&L '!H29/'P&L '!$H$8 -> 0.42849461
A31: PAT | B31: ='P&L '!B34/'P&L '!$B$8 -> 0.55058674 | C31: ='P&L '!C34/'P&L '!$C$8 -> 0.31663772 | D31: ='P&L '!D34/'P&L '!$D$8 -> 0.2910856 | E31: ='P&L '!E34/'P&L '!$E$8 -> 0.24602949 | F31: ='P&L '!F34/'P&L '!$F$8 -> 0.28431343 | G31: ='P&L '!G34/'P&L '!$F$8 -> -0.045608019 | H31: ='P&L '!H34/'P&L '!$F$8 -> 0.62320791

Sheet Common Size B&L
A3: Hindustan Zinc | B3: 44286 | C3: 44651 | D3: 45016 | E3: 45382 | F3: 45747 | G3: 46112 | H3: 46477
A4: Common Size B&L | B4: Y | C4: Y | D4: Y | E4: Y | F4: Y | G4: Y | H4: Y
A5: (in INR Crores) | B5: Act | C5: Act | D5: Act | E5: Act | F5: Act | G5: Est | H5: Est
A7: ASSETS | J7: Assets
A8: Non-current asset | J8: Fixed assets form the largest portion → business is asset-heavy and capital intensive.
A9: Property, plant and equipment | B9: ='Balance sheet'!B8/'Balance sheet'!$B$34 -> 0.35967809 | C9: ='Balance sheet'!C8/'Balance sheet'!$C$34 -> 0.38426237 | D9: ='Balance sheet'!D8/'Balance sheet'!$D$34 -> 0.49426227 | E9: ='Balance sheet'!E8/'Balance sheet'!$E$34 -> 0.53019619 | F9: ='Balance sheet'!F8/'Balance sheet'!$F$34 -> 0.53595245 | G9: ='Balance sheet'!G8/'Balance sheet'!$G$34 -> 0.56620651 | H9: ='Balance sheet'!H8/'Balance sheet'!$H$34 -> 0.50131597 | J9: Share of fixed assets increases over time → expansion and capacity growth.
A10: Capital work-in-progress | B10: ='Balance sheet'!B9/'Balance sheet'!$B$34 -> 0.04203206 | C10: ='Balance sheet'!C9/'Balance sheet'!$C$34 -> 0.046451757 | D10: ='Balance sheet'!D9/'Balance sheet'!$D$34 -> 0.063072715 | E10: ='Balance sheet'!E9/'Balance sheet'!$E$34 -> 0.050036879 | F10: ='Balance sheet'!F9/'Balance sheet'!$F$34 -> 0.075558133 | G10: ='Balance sheet'!G9/'Balance sheet'!$G$34 -> 0.079083207 | H10: ='Balance sheet'!H9/'Balance sheet'!$H$34 -> 0.069699306 | J10: Current assets fluctuate → working capital adjusts with operations.
A11: Intangible Assets | B11: ='Balance sheet'!B10/'Balance sheet'!$B$34 -> 0.0078946793 | C11: ='Balance sheet'!C10/'Balance sheet'!$C$34 -> 0.0051712559 | D11: ='Balance sheet'!D10/'Balance sheet'!$D$34 -> 0.0025939606 | E11: ='Balance sheet'!E10/'Balance sheet'!$E$34 -> 0.0053105178 | F11: ='Balance sheet'!F10/'Balance sheet'!$F$34 -> 0.0035662511 | G11: ='Balance sheet'!G10/'Balance sheet'!$G$34 -> 0.0037326302 | H11: ='Balance sheet'!H10/'Balance sheet'!$H$34 -> 0.0032897217 | J11: Cash proportion is relatively low → funds are mostly deployed, not idle.
A12: Financial assets
A13: Investments | B13: ='Balance sheet'!B12/'Balance sheet'!$B$34 -> 0 | C13: ='Balance sheet'!C12/'Balance sheet'!$C$34 -> 0 | D13: ='Balance sheet'!D12/'Balance sheet'!$D$34 -> 0.0072461725 | E13: ='Balance sheet'!E12/'Balance sheet'!$E$34 -> 0.017052663 | F13: ='Balance sheet'!F12/'Balance sheet'!$F$34 -> 0.023861989 | G13: ='Balance sheet'!G12/'Balance sheet'!$G$34 -> 0.024975241 | H13: ='Balance sheet'!H12/'Balance sheet'!$H$34 -> 0.022011715
A14: Loans | B14: ='Balance sheet'!B13/'Balance sheet'!$B$34 -> 0.00026242701 | C14: ='Balance sheet'!C13/'Balance sheet'!$C$34 -> 4.4772778e-05 | D14: ='Balance sheet'!D13/'Balance sheet'!$D$34 -> 0 | E14: ='Balance sheet'!E13/'Balance sheet'!$E$34 -> 0 | F14: ='Balance sheet'!F13/'Balance sheet'!$F$34 -> 2.8993911e-05 | G14: ='Balance sheet'!G13/'Balance sheet'!$G$34 -> 3.0346587e-05 | H14: ='Balance sheet'!H13/'Balance sheet'!$H$34 -> 2.6745705e-05
A15: Others | B15: ='Balance sheet'!B14/'Balance sheet'!$B$34 -> 0.00094036346 | C15: ='Balance sheet'!C14/'Balance sheet'!$C$34 -> 0.0012536378 | D15: ='Balance sheet'!D14/'Balance sheet'!$D$34 -> 0.0031578651 | E15: ='Balance sheet'!E14/'Balance sheet'!$E$34 -> 0.0038648768 | F15: ='Balance sheet'!F14/'Balance sheet'!$F$34 -> 0.0027544216 | G15: ='Balance sheet'!G14/'Balance sheet'!$G$34 -> 0.0028829258 | H15: ='Balance sheet'!H14/'Balance sheet'!$H$34 -> 0.0025408419
A16: Deferred tax assets (net) | B16: ='Balance sheet'!B15/'Balance sheet'!$B$34 -> 0.023137315 | C16: ='Balance sheet'!C15/'Balance sheet'!$C$34 -> 0 | D16: ='Balance sheet'!D15/'Balance sheet'!$D$34 -> 0 | E16: ='Balance sheet'!E15/'Balance sheet'!$E$34 -> 0 | F16: ='Balance sheet'!F15/'Balance sheet'!$F$34 -> 0 | G16: ='Balance sheet'!G15/'Balance sheet'!$G$34 -> 0 | H16: ='Balance sheet'!H15/'Balance sheet'!$H$34 -> 0
A17: Other non-current assets | B17: ='Balance sheet'!B16/'Balance sheet'!$B$34 -> 0.0094255035 | C17: ='Balance sheet'!C16/'Balance sheet'!$C$34 -> 0.006156257 | D17: ='Balance sheet'!D16/'Balance sheet'!$D$34 -> 0.0081766149 | E17: ='Balance sheet'!E16/'Balance sheet'!$E$34 -> 0.016787137 | F17: ='Balance sheet'!F16/'Balance sheet'!$F$34 -> 0.017135402 | G17: ='Balance sheet'!G16/'Balance sheet'!$G$34 -> 0.017934833 | H17: ='Balance sheet'!H16/'Balance sheet'!$H$34 -> 0.015806711
A18: Income tax assets | B18: ='Balance sheet'!B17/'Balance sheet'!$B$34 -> 0.019353992 | C18: ='Balance sheet'!C17/'Balance sheet'!$C$34 -> 0.019789568 | D18: ='Balance sheet'!D17/'Balance sheet'!$D$34 -> 0.0040883074 | E18: ='Balance sheet'!E17/'Balance sheet'!$E$34 -> 0.0042779171 | F18: ='Balance sheet'!F17/'Balance sheet'!$F$34 -> 0.0040591476 | G18: ='Balance sheet'!G17/'Balance sheet'!$G$34 -> 0.0042485222 | H18: ='Balance sheet'!H17/'Balance sheet'!$H$34 -> 0.0037443987
A19: Total non-current assets | B19: ='Balance sheet'!B18/'Balance sheet'!$B$34 -> 0.46272443 | C19: ='Balance sheet'!C18/'Balance sheet'!$B$34 -> 0.45242417 | D19: ='Balance sheet'!D18/'Balance sheet'!$B$34 -> 0.45187745 | E19: ='Balance sheet'!E18/'Balance sheet'!$B$34 -> 0.46515188 | F19: ='Balance sheet'!F18/'Balance sheet'!$B$34 -> 0.50001093 | G19: ='Balance sheet'!G18/'Balance sheet'!$G$34 -> 0.69909421 | H19: ='Balance sheet'!H18/'Balance sheet'!$G$34 -> 0.70169788
A21: current assets
A22: Inventories | B22: ='Balance sheet'!B21/'Balance sheet'!$B$34 -> 0.031163208 | C22: ='Balance sheet'!C21/'Balance sheet'!$C$34 -> 0.043720618 | D22: ='Balance sheet'!D21/'Balance sheet'!$D$34 -> 0.052499507 | E22: ='Balance sheet'!E21/'Balance sheet'!$E$34 -> 0.05682254 | F22: ='Balance sheet'!F21/'Balance sheet'!$F$34 -> 0.054769498 | G22: ='Balance sheet'!G21/'Balance sheet'!$G$34 -> 0.0074619809 | H22: ='Balance sheet'!H21/'Balance sheet'!$H$34 -> 0.10484328
A23: Financial Assets
A24: Investments | B24: ='Balance sheet'!B24/'Balance sheet'!$B$34 -> 0.28335557 | C24: ='Balance sheet'!C24/'Balance sheet'!$C$34 -> 0.33695993 | D24: ='Balance sheet'!D24/'Balance sheet'!$D$34 -> 0.27772295 | E24: ='Balance sheet'!E24/'Balance sheet'!$E$34 -> 0.2913114 | F24: ='Balance sheet'!F24/'Balance sheet'!$F$34 -> 0.26526529 | G24: ='Balance sheet'!G23/'Balance sheet'!$G$34 -> 0 | H24: ='Balance sheet'!H23/'Balance sheet'!$H$34 -> 0
A25: Trade receivables | B25: ='Balance sheet'!B25/'Balance sheet'!$B$34 -> 0.0088787806 | C25: ='Balance sheet'!C25/'Balance sheet'!$C$34 -> 0.016028655 | D25: ='Balance sheet'!D25/'Balance sheet'!$D$34 -> 0.010714185 | E25: ='Balance sheet'!E25/'Balance sheet'!$E$34 -> 0.0045729459 | F25: ='Balance sheet'!F25/'Balance sheet'!$F$34 -> 0.0033922876 | G25: ='Balance sheet'!G24/'Balance sheet'!$G$34 -> 0.27764093 | H25: ='Balance sheet'!H24/'Balance sheet'!$H$34 -> 0.24469645
A26: Cash and cash equivalents | B26: ='Balance sheet'!B27/'Balance sheet'!$B$34 -> 0.0068449712 | C26: ='Balance sheet'!C27/'Balance sheet'!$C$34 -> 0.035639131 | D26: ='Balance sheet'!D27/'Balance sheet'!$D$34 -> 0.0016635182 | E26: ='Balance sheet'!E27/'Balance sheet'!$E$34 -> 0.0015636525 | F26: ='Balance sheet'!F27/'Balance sheet'!$F$34 -> 0.0027834155 | G26: ='Balance sheet'!G25/'Balance sheet'!$G$34 -> 0.0015096374 | H26: ='Balance sheet'!H25/'Balance sheet'!$H$34 -> 0.019427624
A27: Other Bank balances | B27: ='Balance sheet'!B28/'Balance sheet'!$B$34 -> 0.198198 | C27: ='Balance sheet'!C28/'Balance sheet'!$C$34 -> 0.093373629 | D27: ='Balance sheet'!D28/'Balance sheet'!$D$34 -> 0.038148138 | E27: ='Balance sheet'!E28/'Balance sheet'!$E$34 -> 0.0035993509 | F27: ='Balance sheet'!F28/'Balance sheet'!$F$34 -> 0.0023485068 | G27: ='Balance sheet'!G26/'Balance sheet'!$G$34 -> 3.8689802e-07 | H27: ='Balance sheet'!H26/'Balance sheet'!$H$34 -> 3.107887e-07
A28: Loans | B28: ='Balance sheet'!B29/'Balance sheet'!$B$34 -> 4.3737835e-05 | C28: ='Balance sheet'!C29/'Balance sheet'!$C$34 -> 4.4772778e-05 | D28: ='Balance sheet'!D29/'Balance sheet'!$D$34 -> 8.4585671e-05 | E28: ='Balance sheet'!E29/'Balance sheet'!$E$34 -> 2.9502877e-05 | F28: ='Balance sheet'!F29/'Balance sheet'!$F$34 -> 2.8993911e-05 | G28: ='Balance sheet'!G27/'Balance sheet'!$G$34 -> 0.0029132724 | H28: ='Balance sheet'!H27/'Balance sheet'!$H$34 -> 0.0025675876
A29: Others | B29: ='Balance sheet'!B30/'Balance sheet'!$B$34 -> 0.0011590526 | C29: ='Balance sheet'!C30/'Balance sheet'!$C$34 -> 0.00073875084 | D29: ='Balance sheet'!D30/'Balance sheet'!$D$34 -> 0.0025093749 | E29: ='Balance sheet'!E30/'Balance sheet'!$E$34 -> 0.0017406697 | F29: ='Balance sheet'!F30/'Balance sheet'!$F$34 -> 0.0011887504 | G29: ='Balance sheet'!G28/'Balance sheet'!$G$34 -> 0.0024580736 | H29: ='Balance sheet'!H28/'Balance sheet'!$H$34 -> 0.0021664021
A30: Income tax assets | B30: ='Balance sheet'!B31/'Balance sheet'!$B$34 -> 0 | C30: ='Balance sheet'!C31/'Balance sheet'!$C$34 -> 0 | D30: ='Balance sheet'!D31/'Balance sheet'!$D$34 -> 0.024586235 | E30: ='Balance sheet'!E31/'Balance sheet'!$E$34 -> 0 | F30: ='Balance sheet'!F31/'Balance sheet'!$F$34 -> 2.8993911e-05 | G30: ='Balance sheet'!G29/'Balance sheet'!$G$34 -> 3.0346587e-05 | H30: ='Balance sheet'!H29/'Balance sheet'!$H$34 -> 2.6745705e-05
A31: Other current assets | B31: ='Balance sheet'!B32/'Balance sheet'!$B$34 -> 0.0076322523 | C31: ='Balance sheet'!C32/'Balance sheet'!$C$34 -> 0.010364898 | D31: ='Balance sheet'!D32/'Balance sheet'!$D$34 -> 0.0094735952 | E31: ='Balance sheet'!E32/'Balance sheet'!$E$34 -> 0.012833751 | F31: ='Balance sheet'!F32/'Balance sheet'!$F$34 -> 0.0072774717 | G31: ='Balance sheet'!G30/'Balance sheet'!$G$34 -> 0.0012442101 | H31: ='Balance sheet'!H30/'Balance sheet'!$H$34 -> 0.0010965739
A32: Total current assets | B32: ='Balance sheet'!B33/'Balance sheet'!$B$34 -> 0.53727557 | C32: ='Balance sheet'!C33/'Balance sheet'!$C$34 -> 0.53687038 | D32: ='Balance sheet'!D33/'Balance sheet'!$D$34 -> 0.41740209 | E32: ='Balance sheet'!E33/'Balance sheet'!$E$34 -> 0.37247382 | F32: ='Balance sheet'!F33/'Balance sheet'!$F$34 -> 0.33708321 | G32: ='Balance sheet'!G31/'Balance sheet'!$G$34 -> 3.0346587e-05 | H32: ='Balance sheet'!H31/'Balance sheet'!$H$34 -> 2.6745705e-05
A33: TOTAL | B33: ='Balance sheet'!B34/'Balance sheet'!$B$34 -> 1 | C33: ='Balance sheet'!C34/'Balance sheet'!$C$34 -> 1 | D33: ='Balance sheet'!D34/'Balance sheet'!$D$34 -> 1 | E33: ='Balance sheet'!E34/'Balance sheet'!$E$34 -> 1 | F33: ='Balance sheet'!F34/'Balance sheet'!$F$34 -> 1 | G33: ='Balance sheet'!G32/'Balance sheet'!$G$34 -> 0.0076169934 | H33: ='Balance sheet'!H32/'Balance sheet'!$H$34 -> 0.0067131719
A35: EQUITY AND LIABILITES | J35: Liabilities & Equity
A36: equity | J36: Equity contributes a major share → strong financial foundation.
A37: Equity share capital | B37: ='Balance sheet'!B38/'Balance sheet'!$B$34 -> 0.018479235 | C37: ='Balance sheet'!C38/'Balance sheet'!$C$34 -> 0.018916499 | D37: ='Balance sheet'!D38/'Balance sheet'!$D$34 -> 0.023824964 | E37: ='Balance sheet'!E38/'Balance sheet'!$E$34 -> 0.024929931 | F37: ='Balance sheet'!F38/'Balance sheet'!$F$34 -> 0.024499855 | G37: ='Balance sheet'!G36/'Balance sheet'!$G$34 -> 0 | H37: ='Balance sheet'!H36/'Balance sheet'!$H$34 -> 0 | J37: Debt portion is moderate → leverage is controlled
A38: Other equity | B38: ='Balance sheet'!B39/'Balance sheet'!$B$34 -> 0.6881711 | C38: ='Balance sheet'!C39/'Balance sheet'!$C$34 -> 0.74851131 | D38: ='Balance sheet'!D39/'Balance sheet'!$D$34 -> 0.34079567 | E38: ='Balance sheet'!E39/'Balance sheet'!$E$34 -> 0.42336628 | F38: ='Balance sheet'!F39/'Balance sheet'!$F$34 -> 0.36187301 | G38: ='Balance sheet'!G37/'Balance sheet'!$G$34 -> 0 | H38: ='Balance sheet'!H37/'Balance sheet'!$H$34 -> 0 | J38: Current liabilities move with business activity → normal operating cycle effect.
A39: Total equity | B39: ='Balance sheet'!B40/'Balance sheet'!$B$34 -> 0.70665034 | C39: ='Balance sheet'!C40/'Balance sheet'!$C$34 -> 0.7674278 | D39: ='Balance sheet'!D40/'Balance sheet'!$D$34 -> 0.36462063 | E39: ='Balance sheet'!E40/'Balance sheet'!$E$34 -> 0.44829621 | F39: ='Balance sheet'!F40/'Balance sheet'!$F$34 -> 0.38637286 | G39: ='Balance sheet'!G38/'Balance sheet'!$G$34 -> 0.025642866 | H39: ='Balance sheet'!H38/'Balance sheet'!$H$34 -> 0.02260012 | J39: No sharp spike in borrowings → disciplined financing approach.
A41: Liabilities
A42: non-current liabilities
A43: Financial liabilities
A44: Borrowings | B44: ='Balance sheet'!B45/'Balance sheet'!$B$34 -> 0.094298773 | C44: ='Balance sheet'!C45/'Balance sheet'!$C$34 -> 0.047257667 | D44: ='Balance sheet'!D45/'Balance sheet'!$D$34 -> 0.042292836 | E44: ='Balance sheet'!E45/'Balance sheet'!$E$34 -> 0.12526921 | F44: ='Balance sheet'!F45/'Balance sheet'!$F$34 -> 0.17367353 | G44: ='Balance sheet'!G43/'Balance sheet'!$G$34 -> 0 | H44: ='Balance sheet'!H43/'Balance sheet'!$H$34 -> 0
A45: Lease Liabilities | B45: ='Balance sheet'!B46/'Balance sheet'!$B$34 -> 0 | C45: ='Balance sheet'!C46/'Balance sheet'!$C$34 -> 0.00013431833 | D45: ='Balance sheet'!D46/'Balance sheet'!$D$34 -> 0.00053570925 | E45: ='Balance sheet'!E46/'Balance sheet'!$E$34 -> 0.005251512 | F45: ='Balance sheet'!F46/'Balance sheet'!$F$34 -> 0.0051609162 | G45: ='Balance sheet'!G44/'Balance sheet'!$G$34 -> 0 | H45: ='Balance sheet'!H44/'Balance sheet'!$H$34 -> 0
A46: Other financial liabilities | B46: ='Balance sheet'!B47/'Balance sheet'!$B$34 -> 0.00017495134 | C46: ='Balance sheet'!C47/'Balance sheet'!$C$34 -> 0 | D46: ='Balance sheet'!D47/'Balance sheet'!$D$34 -> 0 | E46: ='Balance sheet'!E47/'Balance sheet'!$E$34 -> 0 | F46: ='Balance sheet'!F47/'Balance sheet'!$F$34 -> 0.0099159177 | G46: ='Balance sheet'!G45/'Balance sheet'!$G$34 -> 0.18177606 | H46: ='Balance sheet'!H45/'Balance sheet'!$H$34 -> 0.16020677
A47: Other non-current liabilities | B47: ='Balance sheet'!B48/'Balance sheet'!$B$34 -> 0.022656199 | C47: ='Balance sheet'!C48/'Balance sheet'!$C$34 -> 0.022923662 | D47: ='Balance sheet'!D48/'Balance sheet'!$D$34 -> 0.029886937 | E47: ='Balance sheet'!E48/'Balance sheet'!$E$34 -> 0.027290161 | F47: ='Balance sheet'!F48/'Balance sheet'!$F$34 -> 0.027921137 | G47: ='Balance sheet'!G46/'Balance sheet'!$G$34 -> 0.0054016925 | H47: ='Balance sheet'!H46/'Balance sheet'!$H$34 -> 0.0047607354
A48: Provisions | B48: ='Balance sheet'!B49/'Balance sheet'!$B$34 -> 0.003980143 | C48: ='Balance sheet'!C49/'Balance sheet'!$C$34 -> 0.0047459145 | D48: ='Balance sheet'!D49/'Balance sheet'!$D$34 -> 0.0053288973 | E48: ='Balance sheet'!E49/'Balance sheet'!$E$34 -> 0.0058710724 | F48: ='Balance sheet'!F49/'Balance sheet'!$F$34 -> 0.0057987823 | G48: ='Balance sheet'!G47/'Balance sheet'!$G$34 -> 0.010378533 | H48: ='Balance sheet'!H47/'Balance sheet'!$H$34 -> 0.009147031
A49: Deferred tax liabilities | B49: ='Balance sheet'!B50/'Balance sheet'!$B$34 -> 0 | C49: ='Balance sheet'!C50/'Balance sheet'!$C$34 -> 0.021087979 | D49: ='Balance sheet'!D50/'Balance sheet'!$D$34 -> 0.065243748 | E49: ='Balance sheet'!E50/'Balance sheet'!$E$34 -> 0.068181148 | F49: ='Balance sheet'!F50/'Balance sheet'!$F$34 -> 0.066454045 | G49: ='Balance sheet'!G48/'Balance sheet'!$G$34 -> 0.029223764 | H49: ='Balance sheet'!H48/'Balance sheet'!$H$34 -> 0.025756114
A50: Total non-current liabilities | B50: ='Balance sheet'!B51/'Balance sheet'!$B$34 -> 0.12111007 | C50: ='Balance sheet'!C51/'Balance sheet'!$C$34 -> 0.096149541 | D50: ='Balance sheet'!D51/'Balance sheet'!$D$34 -> 0.14328813 | E50: ='Balance sheet'!E51/'Balance sheet'!$E$34 -> 0.23186311 | F50: ='Balance sheet'!F51/'Balance sheet'!$F$34 -> 0.28892433 | G50: ='Balance sheet'!G49/'Balance sheet'!$G$34 -> 0.0060693175 | H50: ='Balance sheet'!H49/'Balance sheet'!$H$34 -> 0.0053491409
A52: current liabilities
A53: Financial liabilities
A54: Lease Liabilities | B54: ='Balance sheet'!B55/'Balance sheet'!$B$34 -> 0 | C54: ='Balance sheet'!C55/'Balance sheet'!$C$34 -> 0.00033579584 | D54: ='Balance sheet'!D55/'Balance sheet'!$D$34 -> 0.0005920997 | E54: ='Balance sheet'!E55/'Balance sheet'!$E$34 -> 0.0025962531 | F54: ='Balance sheet'!F55/'Balance sheet'!$F$34 -> 0.0040011598 | G54: ='Balance sheet'!G53/'Balance sheet'!$G$34 -> 0 | H54: ='Balance sheet'!H53/'Balance sheet'!$H$34 -> 0
A55: Borrowing | B55: ='Balance sheet'!B56/'Balance sheet'!$B$34 -> 0.047258731 | C55: ='Balance sheet'!C56/'Balance sheet'!$C$34 -> 0.015939109 | D55: ='Balance sheet'!D56/'Balance sheet'!$D$34 -> 0.29156681 | E55: ='Balance sheet'!E56/'Balance sheet'!$E$34 -> 0.12420711 | F55: ='Balance sheet'!F56/'Balance sheet'!$F$34 -> 0.13514062 | G55: ='Balance sheet'!G54/'Balance sheet'!$G$34 -> 0 | H55: ='Balance sheet'!H54/'Balance sheet'!$H$34 -> 0
A56: Operational buyers' credit/ suppliers' credit | B56: ='Balance sheet'!B57/'Balance sheet'!$B$34 -> 0 | C56: ='Balance sheet'!C57/'Balance sheet'!$C$34 -> 0.0062681889 | D56: ='Balance sheet'!D57/'Balance sheet'!$D$34 -> 0.0086559337 | E56: ='Balance sheet'!E57/'Balance sheet'!$E$34 -> 0.011771648 | F56: ='Balance sheet'!F57/'Balance sheet'!$F$34 -> 0.016497536 | G56: ='Balance sheet'!G55/'Balance sheet'!$G$34 -> 0.0041878291 | H56: ='Balance sheet'!H55/'Balance sheet'!$H$34 -> 0.0036909072
A57: Trade payables
A58: a) Total outstanding dues of Micro, Small and Medium Enterprises | B58: ='Balance sheet'!B59/'Balance sheet'!$B$34 -> 0.00083101887 | C58: ='Balance sheet'!C59/'Balance sheet'!$C$34 -> 0.045623461 | D58: ='Balance sheet'!D59/'Balance sheet'!$D$34 -> 0.058871627 | E58: ='Balance sheet'!E59/'Balance sheet'!$E$34 -> 0.062133058 | F58: ='Balance sheet'!F59/'Balance sheet'!$F$34 -> 0.06390258 | G58: ='Balance sheet'!G57/'Balance sheet'!$G$34 -> 0.017267208 | H58: ='Balance sheet'!H57/'Balance sheet'!$H$34 -> 0.015218306
A59: b) Total outstanding dues to creditors other than Micro | B59: ='Balance sheet'!B61/'Balance sheet'!$B$34 -> 0.032956459 | C59: ='Balance sheet'!C61/'Balance sheet'!$C$34 -> 0 | D59: ='Balance sheet'!D61/'Balance sheet'!$D$34 -> 0 | E59: ='Balance sheet'!E61/'Balance sheet'!$E$34 -> 0 | F59: ='Balance sheet'!F61/'Balance sheet'!$F$34 -> 0 | G59: ='Balance sheet'!G58/'Balance sheet'!$G$34 -> 0 | H59: ='Balance sheet'!H58/'Balance sheet'!$H$34 -> 0
A60: Other financial liabilities | B60: ='Balance sheet'!B63/'Balance sheet'!$B$34 -> 0.043103637 | C60: ='Balance sheet'!C63/'Balance sheet'!$C$34 -> 0.042556526 | D60: ='Balance sheet'!D63/'Balance sheet'!$D$34 -> 0.068204246 | E60: ='Balance sheet'!E63/'Balance sheet'!$E$34 -> 0.041717067 | F60: ='Balance sheet'!F63/'Balance sheet'!$F$34 -> 0.049782546 | G60: ='Balance sheet'!G59/'Balance sheet'!$G$34 -> 0.0064840815 | H60: ='Balance sheet'!H59/'Balance sheet'!$H$34 -> 0.11056021
A61: Other current liabilities | B61: ='Balance sheet'!B64/'Balance sheet'!$B$34 -> 0.042578783 | C61: ='Balance sheet'!C64/'Balance sheet'!$C$34 -> 0.019252295 | D61: ='Balance sheet'!D64/'Balance sheet'!$D$34 -> 0.047565342 | E61: ='Balance sheet'!E64/'Balance sheet'!$E$34 -> 0.062723116 | F61: ='Balance sheet'!F64/'Balance sheet'!$F$34 -> 0.045781386 | G61: ='Balance sheet'!G60/'Balance sheet'!$G$34 -> 7.6773762e-06 | H61: ='Balance sheet'!H60/'Balance sheet'!$H$34 -> 8.0744066e-06 | J61: Structure Insight
A62: Income tax liabilities | B62: ='Balance sheet'!B65/'Balance sheet'!$B$34 -> 0 | C62: ='Balance sheet'!C65/'Balance sheet'!$C$34 -> 0.0057309156 | D62: ='Balance sheet'!D65/'Balance sheet'!$D$34 -> 0.015902106 | E62: ='Balance sheet'!E65/'Balance sheet'!$E$34 -> 0.014072872 | F62: ='Balance sheet'!F65/'Balance sheet'!$F$34 -> 0 | G62: ='Balance sheet'!G61/'Balance sheet'!$G$34 -> 0.0017200683 | H62: ='Balance sheet'!H61/'Balance sheet'!$H$34 -> 0.004915554 | J62: Asset mix is long-term focused while funding is largely stable equity.
A63: Provisions | B63: ='Balance sheet'!B66/'Balance sheet'!$B$34 -> 0.0015308242 | C63: ='Balance sheet'!C66/'Balance sheet'!$C$34 -> 0.00071636445 | D63: ='Balance sheet'!D66/'Balance sheet'!$D$34 -> 0.00073307582 | E63: ='Balance sheet'!E66/'Balance sheet'!$E$34 -> 0.00061956041 | F63: ='Balance sheet'!F66/'Balance sheet'!$F$34 -> 0.00055088431 | G63: ='Balance sheet'!G62/'Balance sheet'!$G$34 -> 2.0366202e-06 | H63: ='Balance sheet'!H62/'Balance sheet'!$H$34 -> 3.5899156e-07 | J63: Increasing asset base without excessive debt → sustainable growth pattern.
A64: Current tax liabilities | B64: ='Balance sheet'!B67/'Balance sheet'!$B$34 -> 0.003980143 | C64: ='Balance sheet'!C67/'Balance sheet'!$C$34 -> 0 | D64: ='Balance sheet'!D67/'Balance sheet'!$D$34 -> 0 | E64: ='Balance sheet'!E67/'Balance sheet'!$E$34 -> 0 | F64: ='Balance sheet'!F67/'Balance sheet'!$F$34 -> 0.0090461003 | G64: ='Balance sheet'!G63/'Balance sheet'!$G$34 -> 0.05210509 | H64: ='Balance sheet'!H63/'Balance sheet'!$H$34 -> 0.045922375 | J64: The balance sheet structure shows a stable, expansion-oriented company with strong equity backing, moderate debt, and efficient asset deployment.
A65: Total current liabilities | B65: ='Balance sheet'!B68/'Balance sheet'!$B$34 -> 0.1722396 | C65: ='Balance sheet'!C68/'Balance sheet'!$C$34 -> 0.13642266 | D65: ='Balance sheet'!D68/'Balance sheet'!$D$34 -> 0.49209124 | E65: ='Balance sheet'!E68/'Balance sheet'!$E$34 -> 0.31984068 | F65: ='Balance sheet'!F68/'Balance sheet'!$F$34 -> 0.32470281 | G65: ='Balance sheet'!G64/'Balance sheet'!$G$34 -> 0.047917261 | H65: ='Balance sheet'!H64/'Balance sheet'!$H$34 -> 0.042231468
A66: TOTAL | B66: ='Balance sheet'!B69/'Balance sheet'!$B$34 -> 1 | C66: ='Balance sheet'!C69/'Balance sheet'!$C$34 -> 1 | D66: ='Balance sheet'!D69/'Balance sheet'!$D$34 -> 1 | E66: ='Balance sheet'!E69/'Balance sheet'!$E$34 -> 1 | F66: ='Balance sheet'!F69/'Balance sheet'!$F$34 -> 1 | G66: ='Balance sheet'!G69/'Balance sheet'!$F$34 -> 0.90024395 | H66: ='Balance sheet'!H69/'Balance sheet'!$F$34 -> 1.6129154

Sheet Ratio Analysis
A2: Hindustan Zinc | B2: Formula | C2: 44286 | D2: 44651 | E2: 45016 | F2: 45382 | G2: 45747 | H2: 46112 | I2: 46477
A3: RATIO ANALYSIS | C3: Y | D3: Y | E3: Y | F3: Y | G3: Y | H3: Y | I3: Y
C4: Act | D4: Act | E4: Act | F4: Act | G4: Act | H4: Est | I4: Est
A6: Nunber of share | C6: =8460000/10000000 -> 0.846 | D6: =8450000/10000000 -> 0.845 | E6: =8450000/10000000 -> 0.845 | F6: =8450000/10000000 -> 0.845 | G6: =8450000/10000000 -> 0.845 | H6: =G6 -> 0.845 | I6: =H6 -> 0.845 | J6: News /Qualitative info | M6: LIQUIDITY RATIOS
A7: Dividend Per Share (DPS) | C7: 21.3 | D7: 18 | E7: 75.5 | F7: 13 | G7: 29 | H7: =H8/H6 -> 0 | I7: =I8/I6 -> 74.283618 | M7: Current Ratio
A8: Dividend Total | C8: =C6*C7 -> 18.0198 | D8: =D6*D7 -> 15.21 | E8: =E6*E7 -> 63.7975 | F8: =F6*F7 -> 10.985 | G8: =G6*G7 -> 24.505 | H8: =H25*'P&L '!G34 -> 0 | I8: =I25*'P&L '!H34 -> 62.769658 | J8: Pay out ratio*PAT | M8: Very high in 2021–22 showing excess liquidity
A9: Market Price of Share (MPS) | C9: 264.45 | D9: 310.15 | E9: 292.3 | F9: 292.3 | G9: 461.9 | H9: 461.9 | I9: 461.9 | M9: Sharp fall in 2023 indicates pressure on working capital
M10: Stabilizes near 1 in later years showing adequate liquidity
A11: Liquidity Ratio | M11: Quick Ratio
A12: CURRENT RATIO | B12: CURRENT ASSESTS/CURRENT LIABILITY | C12: ='Balance sheet'!B33/'Balance sheet'!B68 -> 3.1193499 | D12: ='Balance sheet'!C33/'Balance sheet'!C68 -> 3.9353462 | E12: ='Balance sheet'!D33/'Balance sheet'!D68 -> 0.84822094 | F12: ='Balance sheet'!E33/'Balance sheet'!E68 -> 1.1645605 | G12: ='Balance sheet'!F33/'Balance sheet'!F68 -> 1.0381284 | H12: ='Balance sheet'!G33/'Balance sheet'!G68 -> 1.0701852 | I12: ='Balance sheet'!H33/'Balance sheet'!H68 -> 1.07165 | M12: Follows same pattern as current ratio
A13: QUICK RATIO | B13: (CA-INVENTORIES)/CL | C13: =('Balance sheet'!B33-'Balance sheet'!B21)/'Balance sheet'!B68 -> 2.9384205 | D13: =('Balance sheet'!C33-'Balance sheet'!C21)/'Balance sheet'!C68 -> 3.6148671 | E13: =('Balance sheet'!D33-'Balance sheet'!D21)/'Balance sheet'!D68 -> 0.74153441 | F13: =('Balance sheet'!E33-'Balance sheet'!E21)/'Balance sheet'!E68 -> 0.98690158 | G13: =('Balance sheet'!F33-'Balance sheet'!F21)/'Balance sheet'!F68 -> 0.86945263 | H13: =('Balance sheet'!G33-'Balance sheet'!G21)/'Balance sheet'!G68 -> 1.0436463 | I13: =('Balance sheet'!H33-'Balance sheet'!H21)/'Balance sheet'!H68 -> 0.7771905 | M13: Decline after 2022 shows reduced liquid assets
A14: CASH RATIO | B14: (CASH+BANK+INVESTMENT)/CL | C14: =('Balance sheet'!B27+'Balance sheet'!B28+'Balance sheet'!B24)/'Balance sheet'!B68 -> 2.8355764 | D14: =('Balance sheet'!C27+'Balance sheet'!C28+'Balance sheet'!C24)/'Balance sheet'!C68 -> 3.4156547 | E14: =('Balance sheet'!D27+'Balance sheet'!D28+'Balance sheet'!D24)/'Balance sheet'!D68 -> 0.64527588 | F14: =('Balance sheet'!E27+'Balance sheet'!E28+'Balance sheet'!E24)/'Balance sheet'!E68 -> 0.92694401 | G14: =('Balance sheet'!F27+'Balance sheet'!F28+'Balance sheet'!F24)/'Balance sheet'!F68 -> 0.83275292 | H14: =('Balance sheet'!G27+'Balance sheet'!G28+'Balance sheet'!G24)/'Balance sheet'!G68 -> 1.0065461 | I14: =('Balance sheet'!H27+'Balance sheet'!H28+'Balance sheet'!H24)/'Balance sheet'!H68 -> 0.70054227 | M14: Later years indicate controlled short-term solvency
M15: Cash Ratio
A16: ACTIVITY RATIO | M16: Strong cash position initially
A17: DEBTOR TURNOVER RATIO | B17: TRADE REC/NET REVENUE * 365 | C17: ='Balance sheet'!B25/'P&L '!B8*365 -> 6.7142404 | D17: ='Balance sheet'!C25/'P&L '!C8*365 -> 9.0774575 | E17: ='Balance sheet'!D25/'P&L '!D8*365 -> 4.1686704 | F17: ='Balance sheet'!E25/'P&L '!E8*365 -> 2.0146357 | G17: ='Balance sheet'!F25/'P&L '!F8*365 -> 1.2924851 | H17: ='Balance sheet'!G25/'P&L '!G8*365 -> 4.6534978 | I17: ='Balance sheet'!H25/'P&L '!H8*365 -> 4.2413493 | M17: Falls after 2022 suggesting cash utilization
A18: CREDITOR TURNOVER RATIO | B18: TRADE PAY / TOTAL PURCHASE * 365 | C18: =('Balance sheet'!B59+'Balance sheet'!B61)/('P&L '!B11+'P&L '!B12)*365 -> 125.5678 | D18: =('Balance sheet'!C59+'Balance sheet'!C61)/('P&L '!C11+'P&L '!C12)*365 -> 121.56725 | E18: =('Balance sheet'!D59+'Balance sheet'!D61)/('P&L '!D11+'P&L '!D12)*365 -> 97.971462 | F18: =('Balance sheet'!E59+'Balance sheet'!E61)/('P&L '!E11+'P&L '!E12)*365 -> 120.86321 | G18: =('Balance sheet'!F59+'Balance sheet'!F61)/('P&L '!F11+'P&L '!F12)*365 -> 118.21602 | H18: =('Balance sheet'!G59+'Balance sheet'!G61)/('P&L '!G11+'P&L '!G12)*365 -> 116.83715 | I18: =('Balance sheet'!H59+'Balance sheet'!H61)/('P&L '!H11+'P&L '!H12)*365 -> 115.09102 | M18: Slight recovery later shows balanced cash management
A19: INVENTORY TURNOVER RATIO | B19: INVENTORY / COGS * 365 | C19: ='Balance sheet'!B21/'P&L '!B10*365 -> 109.963 | D19: ='Balance sheet'!C21/'P&L '!C10*365 -> 122.0416 | E19: ='Balance sheet'!D21/'P&L '!D10*365 -> 89.003405 | F19: ='Balance sheet'!E21/'P&L '!E10*365 -> 113.33065 | G19: ='Balance sheet'!F21/'P&L '!F10*365 -> 102.2823 | H19: ='Balance sheet'!G21/'P&L '!G10*365 -> 107.32419 | I19: ='Balance sheet'!H21/'P&L '!H10*365 -> 106.79643 | M19: ACTIVITY RATIOS
A20: OPERATING CYCLE | B20: DEBTOR TURNOVER DAY+ INVENTORY TURNOVER DAYS | C20: =C17+C19 -> 116.67724 | D20: =D17+D19 -> 131.11906 | E20: =E17+E19 -> 93.172075 | F20: =F17+F19 -> 115.34528 | G20: =G17+G19 -> 103.57479 | H20: =H17+H19 -> 111.97769 | I20: =I17+I19 -> 111.03778 | M20: Debtor Days
M21: Continuous decline across years
A22: PROFITABILITY RATIO | M22: Indicates faster receivable collection
A23: EARNING PER SHARE (EPS) | B23: PAT/NO OF SHARES | C23: ='P&L '!B34/'Ratio Analysis'!C6 -> 14364.066 | D23: ='P&L '!C34/'Ratio Analysis'!D6 -> 10788.166 | E23: ='P&L '!D34/'Ratio Analysis'!E6 -> 11461.538 | F23: ='P&L '!E34/'Ratio Analysis'!F6 -> 8176.3314 | G23: ='P&L '!F34/'Ratio Analysis'!G6 -> 11117.16 | H23: ='P&L '!G34/'Ratio Analysis'!H6 -> -1783.3545 | I23: ='P&L '!H34/'Ratio Analysis'!I6 -> 24368.536 | M23: Reflects improved credit management
A24: DIVIDEND PER SHARE (DPS) | B24: TOTAL DIVIDENDS/NO OF SHARE | C24: =C8/C6 -> 21.3 | D24: =D8/D6 -> 18 | E24: =E8/E6 -> 75.5 | F24: =F8/F6 -> 13 | G24: =G8/G6 -> 29 | H24: =H8/H6 -> 0 | I24: =I8/I6 -> 74.283618 | M24: Creditor Days
A25: PAY OUT RATIO | B25: DPS/EPS | C25: =C24/C23 -> 0.001482867 | D25: =D24/D23 -> 0.001668495 | E25: =E24/E23 -> 0.0065872483 | F25: =F24/F23 -> 0.0015899551 | G25: =G24/G23 -> 0.0026085799 | H25: =H24/H23 -> 0.0026085799 | I25: =I24/I23 -> 0.0026085799 | M25: Remains high and stable
A26: RENTENTION RATIO | B26: 1-PAYOUT RATIO | C26: =1-C25 -> 0.99851713 | D26: =1-D25 -> 0.99833151 | E26: =1-E25 -> 0.99341275 | F26: =1-F25 -> 0.99841004 | G26: =1-G25 -> 0.99739142 | H26: =1-H25 -> 1 | I26: =1-I25 -> 0.99695166 | M26: Shows strong supplier credit support
A27: EBITDA MARGIN | B27: EBIDTA/NET REVENUE | C27: ='P&L '!B19/'P&L '!B8 -> 0.71786507 | D27: ='P&L '!C19/'P&L '!C8 -> 0.54098645 | E27: ='P&L '!D19/'P&L '!D8 -> 0.50132243 | F27: ='P&L '!E19/'P&L '!E8 -> 0.45602165 | G27: ='P&L '!F19/'P&L '!F8 -> 0.49471868 | H27: ='P&L '!G19/'P&L '!G8 -> 0.49932118 | I27: ='P&L '!H19/'P&L '!H8 -> 0.49847408 | M27: Helps maintain good cash flow position
A28: EBIT MARGIN | B28: EBIT/NET REVENUE | C28: ='P&L '!B25/'P&L '!B8 -> 0.68560555 | D28: ='P&L '!C25/'P&L '!C8 -> 0.48200764 | E28: ='P&L '!D25/'P&L '!D8 -> 0.44466819 | F28: ='P&L '!E25/'P&L '!E8 -> 0.37077131 | G28: ='P&L '!F25/'P&L '!F8 -> 0.41430344 | H28: ='P&L '!G25/'P&L '!G8 -> -0.26667911 | I28: ='P&L '!H25/'P&L '!H8 -> 0.44320116 | M28: Inventory Days
A29: PBT MARGIN | B29: PBT/NET REVENUE | C29: ='P&L '!B29/'P&L '!B8 -> 0.66811653 | D29: ='P&L '!C29/'P&L '!C8 -> 0.4719347 | E29: ='P&L '!D29/'P&L '!D8 -> 0.43465977 | F29: ='P&L '!E29/'P&L '!E8 -> 0.33676376 | G29: ='P&L '!F29/'P&L '!F8 -> 0.3811628 | H29: ='P&L '!G29/'P&L '!G8 -> -0.49095329 | I29: ='P&L '!H29/'P&L '!H8 -> 0.42849461 | M29: Large fluctuations across years
A30: PAT MARGIN | B30: PAT/NET REVENUE | C30: ='P&L '!B34/'P&L '!B8 -> 0.55058674 | D30: ='P&L '!C34/'P&L '!C8 -> 0.31663772 | E30: ='P&L '!D34/'P&L '!D8 -> 0.2910856 | F30: ='P&L '!E34/'P&L '!E8 -> 0.24602949 | G30: ='P&L '!F34/'P&L '!F8 -> 0.28431343 | H30: ='P&L '!G34/'P&L '!G8 -> -0.38620532 | I30: ='P&L '!H34/'P&L '!H8 -> 0.32940612 | M30: Suggests changes in production levels or demand cycles
M31: Indicates inventory management instability
A32: SOLVENCY RATIO | M32: Operating Cycle
A33: DEBT TO EQUITY RATIOS | B33: (NON CURRENT BORROWINGS+SHORT TERM BORROWINGS)/TOTAL EQUITY | C33: =('Balance sheet'!B45)/'Balance sheet'!B40 -> 0.13344474 | D33: =('Balance sheet'!C45)/'Balance sheet'!C40 -> 0.0615793 | E33: =('Balance sheet'!D45)/'Balance sheet'!D40 -> 0.11599134 | F33: =('Balance sheet'!E45)/'Balance sheet'!E40 -> 0.27943402 | G33: =('Balance sheet'!F45)/'Balance sheet'!F40 -> 0.44949722 | H33: =('Balance sheet'!G45)/'Balance sheet'!G40 -> 0.50680826 | I33: =('Balance sheet'!H45)/'Balance sheet'!H40 -> 0.18515136 | M33: Moves mainly with inventory changes
A34: INTEREST COVERAGE RATIO | B34: EBIT/FINANCE COST | C34: ='P&L '!B25/'P&L '!B27 -> 39.202073 | D34: ='P&L '!C25/'P&L '!C27 -> 47.851724 | E34: ='P&L '!D25/'P&L '!D27 -> 44.429429 | F34: ='P&L '!E25/'P&L '!E27 -> 10.902618 | G34: ='P&L '!F25/'P&L '!F27 -> 12.50137 | H34: ='P&L '!G25/'P&L '!G27 -> -1.1890763 | I34: ='P&L '!H25/'P&L '!H27 -> 30.136311 | M34: Longer cycle in some years due to stock build-up
M35: Overall working capital efficiency depends on inventory control
A36: RETURN RATIO
A37: RETURN ON EQUITY | B37: PAT/TOTAL EQUITY | C37: ='P&L '!B34/'Balance sheet'!B40 -> 0.37607155 | D37: ='P&L '!C34/'Balance sheet'!C40 -> 0.2659199 | E37: ='P&L '!D34/'Balance sheet'!D40 -> 0.74891741 | F37: ='P&L '!E34/'Balance sheet'!E40 -> 0.45468904 | G37: ='P&L '!F34/'Balance sheet'!F40 -> 0.70493772 | H37: ='P&L '!G34/'Balance sheet'!G40 -> -0.12750031 | I37: ='P&L '!H34/'Balance sheet'!H40 -> 0.63648215
A38: CAPITAL EMPLOYED | B38: LONG TERM BORROWINGS + SHORT TERM BORROWINGS + TOTAL EQUITY | C38: ='Balance sheet'!B45+'Balance sheet'!B40 -> 36625 | D38: ='Balance sheet'!C45+'Balance sheet'!C40 -> 36392 | E38: ='Balance sheet'!D45+'Balance sheet'!D40 -> 14432 | F38: ='Balance sheet'!E45+'Balance sheet'!E40 -> 19441 | G38: ='Balance sheet'!F45+'Balance sheet'!F40 -> 19316 | H38: ='Balance sheet'!G45+'Balance sheet'!G40 -> 17809.065 | I38: ='Balance sheet'!H45+'Balance sheet'!H40 -> 19441 | M38: PROFITABILITY RATIOS
A39: ROCE (RETURN ON CAPITAL EMP) | B39: EBIT/CAPITAL EMPLOYED | C39: ='P&L '!B25/'Ratio Analysis'!C38 -> 0.41316041 | D39: ='P&L '!C25/'Ratio Analysis'!D38 -> 0.38132007 | E39: ='P&L '!D25/'Ratio Analysis'!E38 -> 1.0251524 | F39: ='P&L '!E25/'Ratio Analysis'!F38 -> 0.53556916 | G39: ='P&L '!F25/'Ratio Analysis'!G38 -> 0.7086871 | H39: ='P&L '!G25/'Ratio Analysis'!H38 -> -0.058428401 | I39: ='P&L '!H25/'Ratio Analysis'!I38 -> 0.41316041 | M39: EPS
A40: RETURN ON ASSESTS (ROA) | B40: PAT/TOTAL ASSESTS | C40: ='P&L '!B34/'Balance sheet'!B34 -> 0.26575109 | D40: ='P&L '!C34/'Balance sheet'!C34 -> 0.20407432 | E40: ='P&L '!D34/'Balance sheet'!D34 -> 0.27307074 | F40: ='P&L '!E34/'Balance sheet'!E34 -> 0.20383537 | G40: ='P&L '!F34/'Balance sheet'!F34 -> 0.2723688 | H40: ='P&L '!G34/'Balance sheet'!G34 -> -0.045730321 | I40: ='P&L '!H34/'Balance sheet'!H34 -> 0.55073184 | M40: Declines from 2021 to 2024
M41: Improves in 2025
A42: VALUATION RATIO | M42: Negative in 2026 then rises again
A43: PE RATIO (PRICE TO EARNING RATIO) | B43: MPS/EPS | C43: =C9/C23 -> 0.018410525 | D43: =D9/D23 -> 0.028749095 | E43: =E9/E23 -> 0.025502685 | F43: =F9/F23 -> 0.03574953 | G43: =G9/G23 -> 0.041548382 | H43: =H9/H23 -> -0.25900627 | I43: =I9/I23 -> 0.01895477 | M43: Shows volatile earnings performance
A44: BOOK VALUE PER SHARE (BVPS) | B44: TOTAL EQUITY/NO OF SHARE | C44: ='Balance sheet'!B40/'Ratio Analysis'!C6 -> 38195.035 | D44: ='Balance sheet'!C40/'Ratio Analysis'!D6 -> 40569.231 | E44: ='Balance sheet'!D40/'Ratio Analysis'!E6 -> 15304.142 | F44: ='Balance sheet'!E40/'Ratio Analysis'!F6 -> 17982.249 | G44: ='Balance sheet'!F40/'Ratio Analysis'!G6 -> 15770.414 | H44: ='Balance sheet'!G40/'Ratio Analysis'!H6 -> 13987.06 | I44: ='Balance sheet'!H40/'Ratio Analysis'!I6 -> 38286.283 | M44: DPS
A45: PB RATIO (PRICE TO BOOK VALUE) | B45: MPS/BVPS | C45: =C9/C44 -> 0.0069236747 | D45: =D9/D44 -> 0.0076449564 | E45: =E9/E44 -> 0.019099405 | F45: =F9/F44 -> 0.016254919 | G45: =G9/G44 -> 0.029289021 | H45: =H9/H44 -> 0.033023381 | I45: =I9/I44 -> 0.0069236747 | M45: Highly fluctuating dividend payments
A46: SALES PER SHARE (SPS) | B46: NET REVENUE /NO OF SHARE | C46: ='P&L '!B8/'Ratio Analysis'!C6 -> 26088.652 | D46: ='P&L '!C8/'Ratio Analysis'!D6 -> 34071.006 | E46: ='P&L '!D8/'Ratio Analysis'!E6 -> 39375.148 | F46: ='P&L '!E8/'Ratio Analysis'!F6 -> 33233.136 | G46: ='P&L '!F8/'Ratio Analysis'!G6 -> 39101.775 | H46: ='P&L '!G8/'Ratio Analysis'!H6 -> 4617.6331 | I46: ='P&L '!H8/'Ratio Analysis'!I6 -> 73977.179 | M46: Indicates flexible dividend policy
A47: PS RATIO ( PRICE TO SALES RATIO) | B47: MPS/SPS | C47: =C9/C46 -> 0.010136591 | D47: =D9/D46 -> 0.0091030479 | E47: =E9/E46 -> 0.0074234642 | F47: =F9/F46 -> 0.0087954384 | G47: =G9/G46 -> 0.011812763 | H47: =H9/H46 -> 0.1000296 | I47: =I9/I46 -> 0.0062438174 | M47: Suggests payout depends on profit and cash position
A48: DIVIDEND YEILD | B48: DPS/MPS | C48: =C7/C9 -> 0.080544526 | D48: =D7/D9 -> 0.058036434 | E48: =E7/E9 -> 0.25829627 | F48: =F7/F9 -> 0.044474855 | G48: =G7/G9 -> 0.062784152 | H48: =H7/H9 -> 0 | I48: =I7/I9 -> 0.16082186 | M48: Payout Ratio
M49: Remains low throughout
B50: SOLVENCY RATIO | M50: Shows company distributes small portion of earnings
B51: Debt–Equity Ratio | M51: Indicates preference for reinvestment
B52: Very low in early years | D52: RETURN RATIOS | H52: VALUATION RATIOS | M52: Retention Ratio
B53: Gradual increase till 2026 | D53: ROE | H53: P/E Ratio | M53: Very high in all years
B54: Indicates rising use of debt financing | D54: Fluctuates widely across years | H54: Moves with earnings changes | M54: Shows strong profit retention for growth
B55: Interest Coverage Ratio | D55: Remains high overall | H55: Negative in 2026 due to loss | M55: Reflects expansion-focused strategy
B56: Very strong initially | D56: Shows strong shareholder return potential | H56: Returns to normal in later year | M56: EBITDA Margin
B57: Weakens later due to lower profits | D57: Capital Employed | H57: BVPS | M57: Steady decline till 2024
B58: Still shows ability to service debt in most years | D58: Increasing trend over time | H58: Falls in middle years | M58: Slight improvement afterward
D59: Indicates higher investment in business | H59: Rises again afterward | M59: Indicates cost pressure followed by recovery
D60: Suggests expansion or funding growth | H60: Shows fluctuations in net worth per share | M60: EBIT Margin
D61: ROCE | H61: P/B Ratio | M61: Falls significantly in middle years
D62: Highly volatile across years | H62: Remains low across years | M62: Shows reduced operating efficiency
D63: Changes reflect profit movement and investment level | H63: Suggests stock not highly overvalued | M63: Recovers slightly in later years
D64: Shows sensitivity to operating performance | H64: Reflects stable market perception | M64: PBT Margin
D65: ROA | H65: Sales per Share | M65: Continuous fall till 2024
D66: Healthy in most years | H66: Overall increasing trend | M66: Small recovery afterward
D67: Drops during low-profit period | H67: Indicates growth in revenue base | M67: Reflects pressure on operating profits
D68: Improves again later showing efficient asset use | H68: Shows expansion of business scale | M68: PAT Margin
H69: P/S Ratio | M69: Drops sharply from 2021 to 2024
H70: Mostly stable across years | M70: Improves in later years
H71: Suggests share price moves with revenue | M71: Shows net profit affected by industry cycle
H72: Indicates steady valuation level
H73: Dividend Yield
H74: Fluctuates significantly
H75: Depends on dividend changes and share price
H76: Shows inconsistent income return to investors

Sheet Revenue model
A2: Hindustan Zinc | B2: 44286 | C2: 44651 | D2: 45016 | E2: 45382 | F2: 45747 | G2: 46112 | H2: 46477
A3: REVENUE MODEL | B3: Y | C3: Y | D3: Y | E3: Y | F3: Y | G3: Y | H3: Y
A4: (in INR Crores) | B4: Act | C4: Act | D4: Act | E4: Act | F4: Act | G4: Est | H4: Est
J5: Total revenue shows an overall upward trend → core demand is growing long term.
A6: Sale of scrap and residuals | B6: 387 | C6: 319 | D6: 410 | E6: 482 | F6: 662 | G6: =G7*F6+F6 -> 741.44 | H6: =H78*G6+G6 -> 741.44 | J6: Scrap sales increase steadily → efficient resource utilization and cost recovery.
A7: % change as YOY | C7: =C6/B6-1 -> -0.17571059 | D7: =D6/C6-1 -> 0.28526646 | E7: =E6/D6-1 -> 0.17560976 | F7: =F6/E6-1 -> 0.37344398 | G7: 0.12 | H7: 0.105 | J7: Export incentives fluctuate → dependent on policy and external trade conditions.
J8: “Other income” grows gradually → additional revenue streams supporting total income
A9: Export incentives | B9: 80 | C9: 205 | D9: 235 | E9: 198 | F9: 183 | G9: =G10*F9+F9 -> 2928 | H9: =H10*G9+G9 -> 61488 | J9: One dip year appears → likely commodity price or volume cycle, not structural weakness.
A10: % change as YOY | C10: =C9/B9-1 -> 1.5625 | D10: =D9/C9-1 -> 0.14634146 | E10: =E9/D9-1 -> -0.15744681 | F10: =F9/E9-1 -> -0.075757576 | G10: 15 | H10: 20 | J10: Forecast years show strong growth → assumption of higher production or price improvement.
A12: Others (unclaimed amount, carbon credits, etc.) | B12: 91 | C12: 126 | D12: 181 | E12: 170 | F12: 197 | G12: =G13*F12+F12 -> 232.46 | H12: =H13*G12+G12 -> 281.2766
A13: % change as YOY | C13: =C12/B12-1 -> 0.38461538 | D13: =D12/C12-1 -> 0.43650794 | E13: =E12/D12-1 -> -0.060773481 | F13: =F12/E12-1 -> 0.15882353 | G13: 0.18 | H13: 0.21
A15: Total | B15: ='P&L '!B6 -> 22071 | C15: ='P&L '!C6 -> 28790 | D15: ='P&L '!D6 -> 33272 | E15: ='P&L '!E6 -> 28082 | F15: ='P&L '!F6 -> 33041 | G15: =G6+G9+G12 -> 3901.9 | H15: =H6+H9+H12 -> 62510.717

Sheet Capex model
A2: Hindustan Zinc | B2: 44286 | C2: 44651 | D2: 45016 | E2: 45382 | F2: 45747 | G2: 46112 | H2: 46477
A3: CAPEX MODEL | B3: Y | C3: Y | D3: Y | E3: Y | F3: Y | G3: Y | H3: Y | L3: Gross block rising → continuous investment in assets.
A4: (in INR Crores) | B4: Act | C4: Act | D4: Act | E4: Act | F4: Act | G4: Est | H4: Est | L4: Net block growing → new capex exceeds depreciation.
L5: Stable growth rate → planned expansion
A6: Gross Block | B6: 31847 | C6: 35037 | D6: 38013 | E6: 41712 | F6: 45585 | G6: =G7*F6+F6 -> 49861.614 | H6: =H7*G6+G6 -> 54460.286 | L6: Depreciation increasing → asset base expanding
A7: % of change of YOY | C7: =C6/B6-1 -> 0.10016642 | D7: =D6/C6-1 -> 0.084938779 | E7: =E6/D6-1 -> 0.097308815 | F7: =F6/E6-1 -> 0.092850978 | G7: =AVERAGE(C7:F7) -> 0.093816248 | H7: =AVERAGE(D7:G7) -> 0.092228705 | L7: Overall: Steady, disciplined capital investment supporting long-term growth.
A8: Accumulated Deperication | B8: 15400 | C8: 17872 | D8: 20483 | E8: 23741 | F8: 27100 | G8: =F8+'P&L '!G23 -> 31203.618 | H8: =G8+'P&L '!H23 -> 35716.492 | I8: last yr dep + curt yr dep
A9: Net Block | B9: =B6-B8 -> 16447 | C9: =C6-C8 -> 17165 | D9: =D6-D8 -> 17530 | E9: =E6-E8 -> 17971 | F9: =F6-F8 -> 18485 | G9: =G6-G8 -> 18657.996 | H9: =H6-H8 -> 18743.794 | I9: GB-AD

Sheet DCF
A1: HINDUSTAN ZINC
A2: DCF VALUATION
A3: (in INR Crores)
A6: CAPM -Capital Assest Pricing Model
A7: ke (Cost of Equity)/Eri | C7: =C8+C9*C10 -> 0.170776
A8: Rf (Risk free rate) | C8: 0.0667
A9: Beta | C9: 1.47
A10: Rp (Risk Premium =(Erm-Rf) | C10: 0.0708
A13: g(f) | C13: ='Ratio Analysis'!H26+'Ratio Analysis'!H37 -> 0.87249969 | E13: Ke > g
A14: g(h) | C14: =(('Ratio Analysis'!I8/'Ratio Analysis'!C8)^(1/7))-1 -> 0.19516686 | E14: closest
A15: g(gdp) | C15: 8.2
A18: GGM | C18: FY26 | D18: FY27
A19: DIVIDEND | C19: ='Ratio Analysis'!H8 -> 0 | D19: ='Ratio Analysis'!I8 -> 62.769658 | E19: =D19*(1+C14)/(C7-C14) -> -3075.7513
A20: YEAR | C20: 1 | D20: 2 | E20: 2
A21: DCF | C21: =C19/(1+$C$7)^C20 -> 0 | D21: =D19/(1+$C$7)^D20 -> 45.793321 | E21: =E19/(1+$C$7)^E20 -> -2243.9005
A22: VALUE OF EQUITY | C22: =C21+D21+E21 -> -2201.6949
A23: TARGET PRICE | C23: =C22/'Ratio Analysis'!H6 -> -2605.5561
A24: CURRENT PRICE AS ON 17/02/26 | C24: 581.1
A25: ANALYST VIEW | C25: UNDERVALUED
A26: BUY/SELL CALL | C26: BUY
A29: FCFE | C29: FY26 | D29: FY27
A30: PAT | C30: ='P&L '!G34 -> -1506.9346 | D30: ='P&L '!H34 -> 20591.413
A31: DEP | C31: ='P&L '!G23 -> 4103.6177 | D31: ='P&L '!H23 -> 4512.8743
A32: CHANGE IN WC | C32: ='Balance sheet'!G76 -> 223.29011 | D32: ='Balance sheet'!H76 -> 303.55313
A33: CAPEX | C33: ='Capex model'!G6-'Capex model'!F6 -> 4276.6137 | D33: ='Capex model'!H6-'Capex model'!G6 -> 4598.6721
A34: NEW DEBT TAKEN | C34: ='Balance sheet'!G56-'Balance sheet'!F56+'Balance sheet'!G45-'Balance sheet'!F45 -> 0 | D34: ='Balance sheet'!H56-'Balance sheet'!G56+'Balance sheet'!H45-'Balance sheet'!G45 -> 0
A35: FCFE | C35: =C30+C31-C32-C33-C34 -> -1903.2207 | D35: 20202.06 | E35: =D35*(1+C14)/(C7-C14) -> -989913.28 | G35: FCFE=PAT+DEP - CHANGES IN WC - CAPEX - NEW DEDT TAKEN =
A36: YAER | C36: 1 | D36: 2 | E36: 2
A37: DCF | C37: =C35/(1+$C$7)^C36 -> -1625.6062 | D37: =D35/(1+$C$7)^D36 -> 14738.322 | E37: =E35/(1+$C$7)^E36 -> -722186.77
A38: VALUE OF EQUITY | C38: =C37+D37+E37 -> -709074.06
A39: TARGET PRICE | C39: =C38/'Ratio Analysis'!H6 -> -839140.89
A40: CURRENT PRICE AS ON 17-02-2026 | C40: =C24 -> 581.1
A41: ANALYST VIEW | C41: UNDERVALUED
A42: BUY/SELL CELL | C42: BUY
A45: WACC CALCULATION | C45: =C46*C47+C48*C49 -> 0.1195798 | G45: KE*WE+KD*WD
A46: Ke | C46: =C7 -> 0.170776
A47: We | C47: ='Balance sheet'!G40/('Balance sheet'!G40+'Balance sheet'!G56+'Balance sheet'!G45) -> 0.52599159
A48: Kd | C48: ='P&L '!G28*(1-'P&L '!G32) -> 0.062769063
A49: Wd | C49: =1-C47 -> 0.47400841
A52: FCFF | C52: FY26 | D52: FY27
A53: PAT | C53: ='P&L '!G34 -> -1506.9346 | D53: ='P&L '!H34 -> 20591.413
A54: DEP | C54: ='P&L '!G23 -> 4103.6177 | D54: ='P&L '!H23 -> 4512.8743
A55: CAHNGE IN WC | C55: ='Balance sheet'!G76 -> 223.29011 | D55: ='Balance sheet'!H76 -> 303.55313
A56: CAPEX | C56: ='Capex model'!G6-'Capex model'!F6 -> 4276.6137 | D56: ='Capex model'!H6-'Capex model'!G6 -> 4598.6721
A57: FINANCE COST | C57: ='P&L '!G27 -> 875.09541 | D57: ='P&L '!H27 -> 919.31697
A58: FCFF | C58: =C53+C54-C55-C56-C57 -> -2778.3161 | D58: =D53+D54-D55-D56-D57 -> 19282.745 | E58: =D58*(1+C14)/(C45-C14) -> -304933.37
A59: YAER | C59: 1 | D59: 2 | E59: 2
A60: DCF | C60: =C58/(1+$C$45)^C59 -> -2481.5704
A61: VALUE OF EQUITY | C61: =C60+D60+E60 -> -2481.5704
A62: TARGET PRICE | C62: =C61/'Ratio Analysis'!H6 -> -2936.7697
A63: CURRENT PRICE ON 17-02-2026 | C63: =C40 -> 581.1
A64: ANALYST VIEW | C64: UNDERVALUED
A65: BUY/SELL CALL | C65: BUY

Sheet RELATIVE VALUATION
A1: Hindustan Zinc
A2: RELATIVE VALUATION | D2: New/Old -1
A3: (in INR )
A4: COMPANY NAME | B4: NET PROFIT MARGIN | C4: OPERATING PROFIT MARGIN | D4: REVENUE GROWTH | E4: ROE | F4: PE
A6: Hindustan Unilever Ltd | B6: ='Ratio Analysis'!G30 -> 0.28431343 | C6: ='Ratio Analysis'!G27 -> 0.49471868 | D6: ='P&L '!F6/'P&L '!E6-1 -> 0.17658999 | E6: ='Ratio Analysis'!G37 -> 0.70493772 | F6: ='Ratio Analysis'!G43 -> 0.041548382
A7: Emami LTD | B7: 21.38 | C7: 24.02 | D7: =3809/3578-1 -> 0.064561207 | E7: 29.92 | F7: 31.38
A8: Patanjali Food Ltd | B8: 3.8 | C8: 5.3 | D8: =34156/31721-1 -> 0.076763028 | E8: 11.44 | F8: 16.76
A10: Industry Standards | B10: =AVERAGE(B6:B8) -> 8.4881045 | C10: =AVERAGE(C6:C8) -> 9.9382396 | D10: =AVERAGE(D6:D8) -> 0.10597141 | E10: =AVERAGE(E6:E8) -> 14.021646 | F10: =AVERAGE(F6:F8) -> 16.060516
A13: INVESTMENT DECISION | B13: Hindustan unilever ltd
B15: HUL: Market leader, strong brands, stable business, low risk.
B16: Emami: Good company but limited product range, moderate risk
B17: Patanjali: Strong brand appeal but less stability, higher risk

Sheet Valuation based on frwd mutlple
A1: Hindustan Zinc
A2: VALUATION BASED ON FORWARD MUTLIPLE
A3: (in INR )
A4: DATE | B4: MPS | C4: EPS | D4: FORWARD PE
H5: Intrinsic Price | J5: =J6*J7 -> 1090.0478
A6: 02/17/2026 | B6: 581.1 | C6: ='Ratio Analysis'!$G$23 -> 11117.16 | D6: =B6/C6 -> 0.052270545 | H6: Estimated EPS | J6: 24368.64
A7: 02/16/2026 | B7: 594.1 | C7: ='Ratio Analysis'!$G$23 -> 11117.16 | D7: =B7/C7 -> 0.053439908 | H7: Average PE | J7: =AVERAGE(D6:D749) -> 0.044731579
A8: 02/13/2026 | B8: 592.85 | C8: ='Ratio Analysis'!$G$23 -> 11117.16 | D8: =B8/C8 -> 0.05332747
A9: 46358 | B9: 623.7 | C9: ='Ratio Analysis'!$G$23 -> 11117.16 | D9: =B9/C9 -> 0.056102459
A10: 46328 | B10: 628.55 | C10: ='Ratio Analysis'!$G$23 -> 11117.16 | D10: =B10/C10 -> 0.056538722 | H10: Current Price on 17-02-26 | K10: =DCF!C40 -> 581.1
A11: 46297 | B11: 617.7 | C11: ='Ratio Analysis'!$G$23 -> 11117.16 | D11: =B11/C11 -> 0.055562753 | H11: Analyst Review | K11: UNDERVALUED
A12: 46267 | B12: 629.1 | C12: ='Ratio Analysis'!$G$23 -> 11117.16 | D12: =B12/C12 -> 0.056588195 | H12: Analyst Call | K12: BUY
A13: 46175 | B13: 608.95 | C13: ='Ratio Analysis'!$G$23 -> 11117.16 | D13: =B13/C13 -> 0.054775681
A14: 46144 | B14: 610.8 | C14: ='Ratio Analysis'!$G$23 -> 11117.16 | D14: =B14/C14 -> 0.054942091
A15: 46114 | B15: 639.25 | C15: ='Ratio Analysis'!$G$23 -> 11117.16 | D15: =B15/C15 -> 0.057501198
A16: 46083 | B16: 628.25 | C16: ='Ratio Analysis'!$G$23 -> 11117.16 | D16: =B16/C16 -> 0.056511736
A17: 46055 | B17: 610.1 | C17: ='Ratio Analysis'!$G$23 -> 11117.16 | D17: =B17/C17 -> 0.054879125
A18: 46024 | B18: 570.1 | C18: ='Ratio Analysis'!$G$23 -> 11117.16 | D18: =B18/C18 -> 0.051281084
A19: 01/30/2026 | B19: 628.5 | C19: ='Ratio Analysis'!$G$23 -> 11117.16 | D19: =B19/C19 -> 0.056534224
A20: 01/29/2026 | B20: 715.2 | C20: ='Ratio Analysis'!$G$23 -> 11117.16 | D20: =B20/C20 -> 0.064332978
A21: 01/28/2026 | B21: 708.2 | C21: ='Ratio Analysis'!$G$23 -> 11117.16 | D21: =B21/C21 -> 0.063703321
A22: 01/27/2026 | B22: 727.2 | C22: ='Ratio Analysis'!$G$23 -> 11117.16 | D22: =B22/C22 -> 0.065412391
A23: 01/23/2026 | B23: 698.7 | C23: ='Ratio Analysis'!$G$23 -> 11117.16 | D23: =B23/C23 -> 0.062848786
A24: 01/22/2026 | B24: 668.25 | C24: ='Ratio Analysis'!$G$23 -> 11117.16 | D24: =B24/C24 -> 0.060109778
A25: 01/21/2026 | B25: 697.55 | C25: ='Ratio Analysis'!$G$23 -> 11117.16 | D25: =B25/C25 -> 0.062745343
A26: 01/20/2026 | B26: 680.75 | C26: ='Ratio Analysis'!$G$23 -> 11117.16 | D26: =B26/C26 -> 0.061234165
A27: 01/19/2026 | B27: 660.4 | C27: ='Ratio Analysis'!$G$23 -> 11117.16 | D27: =B27/C27 -> 0.059403662
A28: 01/16/2026 | B28: 637.75 | C28: ='Ratio Analysis'!$G$23 -> 11117.16 | D28: =B28/C28 -> 0.057366271
A29: 01/14/2026 | B29: 654.2 | C29: ='Ratio Analysis'!$G$23 -> 11117.16 | D29: =B29/C29 -> 0.058845966
A30: 01/13/2026 | B30: 629.85 | C30: ='Ratio Analysis'!$G$23 -> 11117.16 | D30: =B30/C30 -> 0.056655658
A31: 46357 | B31: 628.25 | C31: ='Ratio Analysis'!$G$23 -> 11117.16 | D31: =B31/C31 -> 0.056511736
A32: 46266 | B32: 606.45 | C32: ='Ratio Analysis'!$G$23 -> 11117.16 | D32: =B32/C32 -> 0.054550804
A33: 46235 | B33: 590.75 | C33: ='Ratio Analysis'!$G$23 -> 11117.16 | D33: =B33/C33 -> 0.053138572
A34: 46204 | B34: 630 | C34: ='Ratio Analysis'!$G$23 -> 11117.16 | D34: =B34/C34 -> 0.056669151
A35: 46174 | B35: 643.1 | C35: ='Ratio Analysis'!$G$23 -> 11117.16 | D35: =B35/C35 -> 0.057847509
A36: 46143 | B36: 628.6 | C36: ='Ratio Analysis'!$G$23 -> 11117.16 | D36: =B36/C36 -> 0.056543219
A37: 46054 | B37: 628.8 | C37: ='Ratio Analysis'!$G$23 -> 11117.16 | D37: =B37/C37 -> 0.056561209
A38: 46023 | B38: 611.95 | C38: ='Ratio Analysis'!$G$23 -> 11117.16 | D38: =B38/C38 -> 0.055045534
A39: 12/31/2025 | B39: 612.45 | C39: ='Ratio Analysis'!$G$23 -> 11117.16 | D39: =B39/C39 -> 0.05509051
A40: 12/30/2025 | B40: 625.3 | C40: ='Ratio Analysis'!$G$23 -> 11117.16 | D40: =B40/C40 -> 0.056246381
A41: 12/29/2025 | B41: 618.55 | C41: ='Ratio Analysis'!$G$23 -> 11117.16 | D41: =B41/C41 -> 0.055639211
A42: 12/26/2025 | B42: 636.85 | C42: ='Ratio Analysis'!$G$23 -> 11117.16 | D42: =B42/C42 -> 0.057285315
A43: 12/24/2025 | B43: 624.85 | C43: ='Ratio Analysis'!$G$23 -> 11117.16 | D43: =B43/C43 -> 0.056205903
A44: 12/23/2025 | B44: 609.8 | C44: ='Ratio Analysis'!$G$23 -> 11117.16 | D44: =B44/C44 -> 0.05485214
A45: 12/22/2025 | B45: 606.5 | C45: ='Ratio Analysis'!$G$23 -> 11117.16 | D45: =B45/C45 -> 0.054555301
A46: 12/19/2025 | B46: 588.75 | C46: ='Ratio Analysis'!$G$23 -> 11117.16 | D46: =B46/C46 -> 0.05295867
A47: 12/18/2025 | B47: 592.15 | C47: ='Ratio Analysis'!$G$23 -> 11117.16 | D47: =B47/C47 -> 0.053264504
A48: 12/17/2025 | B48: 578.3 | C48: ='Ratio Analysis'!$G$23 -> 11117.16 | D48: =B48/C48 -> 0.052018682
A49: 12/16/2025 | B49: 567.7 | C49: ='Ratio Analysis'!$G$23 -> 11117.16 | D49: =B49/C49 -> 0.051065201
A50: 12/15/2025 | B50: 568.05 | C50: ='Ratio Analysis'!$G$23 -> 11117.16 | D50: =B50/C50 -> 0.051096684
A51: 46003 | B51: 561.65 | C51: ='Ratio Analysis'!$G$23 -> 11117.16 | D51: =B51/C51 -> 0.050520997
A52: 45973 | B52: 522.65 | C52: ='Ratio Analysis'!$G$23 -> 11117.16 | D52: =B52/C52 -> 0.047012907
A53: 45942 | B53: 512.65 | C53: ='Ratio Analysis'!$G$23 -> 11117.16 | D53: =B53/C53 -> 0.046113397
A54: 45912 | B54: 491.45 | C54: ='Ratio Analysis'!$G$23 -> 11117.16 | D54: =B54/C54 -> 0.044206435
A55: 45881 | B55: 490.45 | C55: ='Ratio Analysis'!$G$23 -> 11117.16 | D55: =B55/C55 -> 0.044116484
A56: 45789 | B56: 498.1 | C56: ='Ratio Analysis'!$G$23 -> 11117.16 | D56: =B56/C56 -> 0.044804609
A57: 45759 | B57: 496.75 | C57: ='Ratio Analysis'!$G$23 -> 11117.16 | D57: =B57/C57 -> 0.044683175
A58: 45728 | B58: 504.4 | C58: ='Ratio Analysis'!$G$23 -> 11117.16 | D58: =B58/C58 -> 0.045371301
A59: 45700 | B59: 495.65 | C59: ='Ratio Analysis'!$G$23 -> 11117.16 | D59: =B59/C59 -> 0.044584229
A60: 45669 | B60: 499.85 | C60: ='Ratio Analysis'!$G$23 -> 11117.16 | D60: =B60/C60 -> 0.044962024
A61: 11/28/2025 | B61: 485.2 | C61: ='Ratio Analysis'!$G$23 -> 11117.16 | D61: =B61/C61 -> 0.043644241
A62: 11/27/2025 | B62: 474.55 | C62: ='Ratio Analysis'!$G$23 -> 11117.16 | D62: =B62/C62 -> 0.042686263
A63: 11/26/2025 | B63: 470.25 | C63: ='Ratio Analysis'!$G$23 -> 11117.16 | D63: =B63/C63 -> 0.042299473
A64: 11/25/2025 | B64: 462.6 | C64: ='Ratio Analysis'!$G$23 -> 11117.16 | D64: =B64/C64 -> 0.041611348
A65: 11/24/2025 | B65: 454 | C65: ='Ratio Analysis'!$G$23 -> 11117.16 | D65: =B65/C65 -> 0.040837769
A66: 11/21/2025 | B66: 458.3 | C66: ='Ratio Analysis'!$G$23 -> 11117.16 | D66: =B66/C66 -> 0.041224558
A67: 11/20/2025 | B67: 472.15 | C67: ='Ratio Analysis'!$G$23 -> 11117.16 | D67: =B67/C67 -> 0.04247038
A68: 11/19/2025 | B68: 476.55 | C68: ='Ratio Analysis'!$G$23 -> 11117.16 | D68: =B68/C68 -> 0.042866165
A69: 11/18/2025 | B69: 475.95 | C69: ='Ratio Analysis'!$G$23 -> 11117.16 | D69: =B69/C69 -> 0.042812194
A70: 11/17/2025 | B70: 483.9 | C70: ='Ratio Analysis'!$G$23 -> 11117.16 | D70: =B70/C70 -> 0.043527305
A71: 11/14/2025 | B71: 487.05 | C71: ='Ratio Analysis'!$G$23 -> 11117.16 | D71: =B71/C71 -> 0.04381065
A72: 11/13/2025 | B72: 495.2 | C72: ='Ratio Analysis'!$G$23 -> 11117.16 | D72: =B72/C72 -> 0.044543751
A73: 46002 | B73: 481.9 | C73: ='Ratio Analysis'!$G$23 -> 11117.16 | D73: =B73/C73 -> 0.043347403
A74: 45972 | B74: 487.5 | C74: ='Ratio Analysis'!$G$23 -> 11117.16 | D74: =B74/C74 -> 0.043851128
A75: 45941 | B75: 484.6 | C75: ='Ratio Analysis'!$G$23 -> 11117.16 | D75: =B75/C75 -> 0.04359027
A76: 45849 | B76: 474.5 | C76: ='Ratio Analysis'!$G$23 -> 11117.16 | D76: =B76/C76 -> 0.042681765
A77: 45819 | B77: 467.2 | C77: ='Ratio Analysis'!$G$23 -> 11117.16 | D77: =B77/C77 -> 0.042025122
A78: 45758 | B78: 473.35 | C78: ='Ratio Analysis'!$G$23 -> 11117.16 | D78: =B78/C78 -> 0.042578321
A79: 45727 | B79: 480.65 | C79: ='Ratio Analysis'!$G$23 -> 11117.16 | D79: =B79/C79 -> 0.043234964
A80: 10/31/2025 | B80: 476.5 | C80: ='Ratio Analysis'!$G$23 -> 11117.16 | D80: =B80/C80 -> 0.042861667
A81: 10/30/2025 | B81: 477.6 | C81: ='Ratio Analysis'!$G$23 -> 11117.16 | D81: =B81/C81 -> 0.042960613
A82: 10/29/2025 | B82: 483.6 | C82: ='Ratio Analysis'!$G$23 -> 11117.16 | D82: =B82/C82 -> 0.043500319
A83: 10/28/2025 | B83: 471.2 | C83: ='Ratio Analysis'!$G$23 -> 11117.16 | D83: =B83/C83 -> 0.042384927
A84: 10/27/2025 | B84: 482.3 | C84: ='Ratio Analysis'!$G$23 -> 11117.16 | D84: =B84/C84 -> 0.043383383
A85: 10/24/2025 | B85: 486.7 | C85: ='Ratio Analysis'!$G$23 -> 11117.16 | D85: =B85/C85 -> 0.043779168
A86: 10/23/2025 | B86: 482.15 | C86: ='Ratio Analysis'!$G$23 -> 11117.16 | D86: =B86/C86 -> 0.04336989
A87: 10/21/2025 | B87: 483.85 | C87: ='Ratio Analysis'!$G$23 -> 11117.16 | D87: =B87/C87 -> 0.043522807
A88: 10/20/2025 | B88: 486.4 | C88: ='Ratio Analysis'!$G$23 -> 11117.16 | D88: =B88/C88 -> 0.043752182
A89: 10/17/2025 | B89: 500.25 | C89: ='Ratio Analysis'!$G$23 -> 11117.16 | D89: =B89/C89 -> 0.044998004
A90: 10/16/2025 | B90: 506.7 | C90: ='Ratio Analysis'!$G$23 -> 11117.16 | D90: =B90/C90 -> 0.045578188
A91: 10/15/2025 | B91: 513.2 | C91: ='Ratio Analysis'!$G$23 -> 11117.16 | D91: =B91/C91 -> 0.04616287
... A93: 10/13/2025 | B93: 505.55 | C93: ='Ratio Analysis'!$G$23 -> 11117.16 | D93: =B93/C93 -> 0.045474745
A94: 45940 | B94: 498.3 | C94: ='Ratio Analysis'!$G$23 -> 11117.16 | D94: =B94/C94 -> 0.0448226
A95: 45910 | B95: 512.25 | C95: ='Ratio Analysis'!$G$23 -> 11117.16 | D95: =B95/C95 -> 0.046077416
A96: 45879 | B96: 490.5 | C96: ='Ratio Analysis'!$G$23 -> 11117.16 | D96: =B96/C96 -> 0.044120981
A97: 45848 | B97: 489.9 | C97: ='Ratio Analysis'!$G$23 -> 11117.16 | D97: =B97/C97 -> 0.044067011
A98: 45818 | B98: 491.5 | C98: ='Ratio Analysis'!$G$23 -> 11117.16 | D98: =B98/C98 -> 0.044210933
A99: 45726 | B99: 491.5 | C99: ='Ratio Analysis'!$G$23 -> 11117.16 | D99: =B99/C99 -> 0.044210933
A100: 45667 | B100: 481.35 | C100: ='Ratio Analysis'!$G$23 -> 11117.16 | D100: =B100/C100 -> 0.04329793
A101: 09/30/2025 | B101: 482.45 | C101: ='Ratio Analysis'!$G$23 -> 11117.16 | D101: =B101/C101 -> 0.043396876
...
